Workbook

Sheet Cover
A1: MAJOR U.S. BANKS Comparable Company Analysis (Comps)
A7: Trading Comps | 8-Bank Peer Group | Portfolio Financial Model | April 2026
B9: PEER GROUP
B10: JPM | C10: JPMorgan Chase
B11: BAC | C11: Bank of America
B12: WFC | C12: Wells Fargo
B13: GS | C13: Goldman Sachs
B14: MS | C14: Morgan Stanley
B15: C | C15: Citigroup
B16: USB | C16: U.S. Bancorp
B17: TFC | C17: Truist Financial
B32: For portfolio / informational purposes only. Not investment advice. Market data approximate as of April 2026. Financial data sourced from FY2024 10-K filings and consensus estimates.
B34: Blue | C34: Hardcoded input
B35: Black | C35: Formula / calculated
B36: Green | C36: Cross-sheet ref

Sheet Raw Data
A1: RAW DATA — Comparable Company Analysis ($M unless noted)
A3: Metric | B3: JPM | C3: BAC | D3: WFC | E3: GS | F3: MS | G3: C | H3: USB | I3: TFC | J3: Mean | K3: Median | L3: Min | M3: Max | N3: Notes / Source
A4: MARKET DATA
A5: Share Price ($) | B5: 240 | C5: 43.5 | D5: 66.2 | E5: 510 | F5: 107 | G5: 69 | H5: 44.5 | I5: 40.2 | J5: =AVERAGE(B5:I5) -> 140.05 | K5: =MEDIAN(B5:I5) -> 67.6 | L5: =MIN(B5:I5) -> 40.2 | M5: =MAX(B5:I5) -> 510 | N5: Source: Market price approx. Apr 2026
A6: Shares Outstanding (M) | B6: 2900 | C6: 7680 | D6: 3850 | E6: 353 | F6: 1540 | G6: 1930 | H6: 1570 | I6: 1420 | J6: =AVERAGE(B6:I6) -> 2655.375 | K6: =MEDIAN(B6:I6) -> 1750 | L6: =MIN(B6:I6) -> 353 | M6: =MAX(B6:I6) -> 7680 | N6: Source: FY2024 10-K diluted shares
A7: Market Cap ($M) | B7: =B5*B6/1000 -> 696 | C7: =C5*C6/1000 -> 334.08 | D7: =D5*D6/1000 -> 254.87 | E7: =E5*E6/1000 -> 180.03 | F7: =F5*F6/1000 -> 164.78 | G7: =G5*G6/1000 -> 133.17 | H7: =H5*H6/1000 -> 69.865 | I7: =I5*I6/1000 -> 57.084 | J7: =AVERAGE(B7:I7) -> 236.23487 | K7: =MEDIAN(B7:I7) -> 172.405 | L7: =MIN(B7:I7) -> 57.084 | M7: =MAX(B7:I7) -> 696 | N7: Calc: Price x Shares / 1000
A8: Total Debt ($M) | B8: 280000 | C8: 230000 | D8: 185000 | E8: 195000 | F8: 210000 | G8: 245000 | H8: 52000 | I8: 45000 | J8: =AVERAGE(B8:I8) -> 180250 | K8: =MEDIAN(B8:I8) -> 202500 | L8: =MIN(B8:I8) -> 45000 | M8: =MAX(B8:I8) -> 280000 | N8: Note: For banks, debt = long-term borrowings (not deposits)
A9: Cash & Equivalents ($M) | B9: 35000 | C9: 22000 | D9: 18000 | E9: 15000 | F9: 13000 | G9: 20000 | H9: 8000 | I9: 6000 | J9: =AVERAGE(B9:I9) -> 17125 | K9: =MEDIAN(B9:I9) -> 16500 | L9: =MIN(B9:I9) -> 6000 | M9: =MAX(B9:I9) -> 35000 | N9: Note: Included in balance sheet; simplified for EV calc
A10: Enterprise Value ($M) | B10: =B7+B8-B9 -> 245696 | C10: =C7+C8-C9 -> 208334.08 | D10: =D7+D8-D9 -> 167254.87 | E10: =E7+E8-E9 -> 180180.03 | F10: =F7+F8-F9 -> 197164.78 | G10: =G7+G8-G9 -> 225133.17 | H10: =H7+H8-H9 -> 44069.865 | I10: =I7+I8-I9 -> 39057.084 | J10: =AVERAGE(B10:I10) -> 163361.23 | K10: =MEDIAN(B10:I10) -> 188672.4 | L10: =MIN(B10:I10) -> 39057.084 | M10: =MAX(B10:I10) -> 245696 | N10: Calc: Market Cap + Total Debt - Cash (simplified)
A12: INCOME STATEMENT (FY2024A)
A13: Net Revenue ($M) | B13: 181014 | C13: 98641 | D13: 78399 | E13: 53512 | F13: 61793 | G13: 80658 | H13: 26978 | I13: 20200 | J13: =AVERAGE(B13:I13) -> 75149.375 | K13: =MEDIAN(B13:I13) -> 70096 | L13: =MIN(B13:I13) -> 20200 | M13: =MAX(B13:I13) -> 181014 | N13: Source: FY2024 10-K total net revenue
A14: Net Income ($M) | B14: 58471 | C14: 27131 | D14: 19723 | E14: 14280 | F14: 13860 | G14: 12695 | H14: 5700 | I14: 4780 | J14: =AVERAGE(B14:I14) -> 19580 | K14: =MEDIAN(B14:I14) -> 14070 | L14: =MIN(B14:I14) -> 4780 | M14: =MAX(B14:I14) -> 58471 | N14: Source: FY2024 10-K net income to common
A15: EPS — FY2024A ($) | B15: 20.15 | C15: 3.52 | D15: 5.12 | E15: 40.54 | F15: 9 | G15: 6.58 | H15: 3.63 | I15: 3.37 | J15: =AVERAGE(B15:I15) -> 11.48875 | K15: =MEDIAN(B15:I15) -> 5.85 | L15: =MIN(B15:I15) -> 3.37 | M15: =MAX(B15:I15) -> 40.54 | N15: Source: FY2024 10-K diluted EPS
A16: EPS — FY2025E ($) | B16: 21.5 | C16: 3.85 | D16: 5.8 | E16: 44 | F16: 9.8 | G16: 7.2 | H16: 3.95 | I16: 3.65 | J16: =AVERAGE(B16:I16) -> 12.46875 | K16: =MEDIAN(B16:I16) -> 6.5 | L16: =MIN(B16:I16) -> 3.65 | M16: =MAX(B16:I16) -> 44 | N16: Source: Bloomberg consensus estimates, Apr 2026
A17: EPS — FY2026E ($) | B17: 23.22 | C17: 4.16 | D17: 6.26 | E17: 47.52 | F17: 10.58 | G17: 7.78 | H17: 4.27 | I17: 3.94 | J17: =AVERAGE(B17:I17) -> 13.46625 | K17: =MEDIAN(B17:I17) -> 7.02 | L17: =MIN(B17:I17) -> 3.94 | M17: =MAX(B17:I17) -> 47.52 | N17: Source: Bloomberg consensus; ~8% average growth implied
A19: BALANCE SHEET & PER SHARE (FY2024A)
A20: Book Value per Share ($) | B20: 108.5 | C20: 34.4 | D20: 53.6 | E20: 333.1 | F20: 62.4 | G20: 101 | H20: 31.5 | I20: 42.5 | J20: =AVERAGE(B20:I20) -> 95.875 | K20: =MEDIAN(B20:I20) -> 58 | L20: =MIN(B20:I20) -> 31.5 | M20: =MAX(B20:I20) -> 333.1 | N20: Source: FY2024 10-K total equity / diluted shares
A21: Tangible Book Value/Share ($) | B21: 93.2 | C21: 25.1 | D21: 41.2 | E21: 312.5 | F21: 52.7 | G21: 90.3 | H21: 24.6 | I21: 30.2 | J21: =AVERAGE(B21:I21) -> 83.725 | K21: =MEDIAN(B21:I21) -> 46.95 | L21: =MIN(B21:I21) -> 24.6 | M21: =MAX(B21:I21) -> 312.5 | N21: Source: FY2024 10-K; TBV excl. goodwill & intangibles
A22: Dividends per Share ($) | B22: 6 | C22: 1.09 | D22: 1.66 | E22: 12.75 | F22: 2.68 | G22: 1.73 | H22: 1.11 | I22: 1.01 | J22: =AVERAGE(B22:I22) -> 3.50375 | K22: =MEDIAN(B22:I22) -> 1.695 | L22: =MIN(B22:I22) -> 1.01 | M22: =MAX(B22:I22) -> 12.75 | N22: Estimated; ~2-3% yield on approx. prices
A24: PROFITABILITY & EFFICIENCY (FY2024A)
A25: Return on Avg. Equity (ROAE %) | B25: 0.172 | C25: 0.091 | D25: 0.112 | E25: 0.125 | F25: 0.138 | G25: 0.067 | H25: 0.121 | I25: 0.097 | J25: =AVERAGE(B25:I25) -> 0.115375 | K25: =MEDIAN(B25:I25) -> 0.1165 | L25: =MIN(B25:I25) -> 0.067 | M25: =MAX(B25:I25) -> 0.172 | N25: Source: FY2024 10-K; Net Income / Avg Common Equity
A26: Return on Avg. Tang. Common Eq. (%) | B26: 0.208 | C26: 0.128 | D26: 0.148 | E26: 0.133 | F26: 0.168 | G26: 0.075 | H26: 0.165 | I26: 0.14 | J26: =AVERAGE(B26:I26) -> 0.145625 | K26: =MEDIAN(B26:I26) -> 0.144 | L26: =MIN(B26:I26) -> 0.075 | M26: =MAX(B26:I26) -> 0.208 | N26: Source: FY2024 10-K; preferred by analysts
A27: Efficiency Ratio (%) | B27: 0.541 | C27: 0.648 | D27: 0.638 | E27: 0.604 | F27: 0.711 | G27: 0.672 | H27: 0.598 | I27: 0.622 | J27: =AVERAGE(B27:I27) -> 0.62925 | K27: =MEDIAN(B27:I27) -> 0.63 | L27: =MIN(B27:I27) -> 0.541 | M27: =MAX(B27:I27) -> 0.711 | N27: Source: FY2024 10-K; Non-Int Exp / Net Revenue (lower=better)
A28: Net Interest Margin (%) | B28: 0.0282 | C28: 0.0195 | D28: 0.0269 | E28: N/A | F28: N/A | G28: 0.0239 | H28: 0.0289 | I28: 0.0305 | J28: =AVERAGE(B28:I28) -> 0.026316667 | K28: =MEDIAN(B28:I28) -> 0.02755 | L28: =MIN(B28:I28) -> 0.0195 | M28: =MAX(B28:I28) -> 0.0305 | N28: Source: FY2024 10-K; NIM on interest-earning assets
A29: CET1 Ratio (%) | B29: 0.155 | C29: 0.136 | D29: 0.118 | E29: 0.148 | F29: 0.155 | G29: 0.136 | H29: 0.104 | I29: 0.108 | J29: =AVERAGE(B29:I29) -> 0.1325 | K29: =MEDIAN(B29:I29) -> 0.136 | L29: =MIN(B29:I29) -> 0.104 | M29: =MAX(B29:I29) -> 0.155 | N29: Source: FY2024 10-K; Common Equity Tier 1 capital ratio

Sheet Trading Multiples
A1: TRADING MULTIPLES — Major U.S. Banks (Sourced from Raw Data)
A3: Multiple | B3: JPM | C3: BAC | D3: WFC | E3: GS | F3: MS | G3: C | H3: USB | I3: TFC | J3: Mean | K3: Median | L3: Min | M3: Max | N3: Formula / Commentary
A4: EARNINGS-BASED MULTIPLES (Primary for Banks)
A5: P/E — FY2024A (x) | B5: =IF('Raw Data'!B15=0,"-",'Raw Data'!B5/'Raw Data'!B15) -> 11.91067 | C5: =IF('Raw Data'!C15=0,"-",'Raw Data'!C5/'Raw Data'!C15) -> 12.357955 | D5: =IF('Raw Data'!D15=0,"-",'Raw Data'!D5/'Raw Data'!D15) -> 12.929688 | E5: =IF('Raw Data'!E15=0,"-",'Raw Data'!E5/'Raw Data'!E15) -> 12.580168 | F5: =IF('Raw Data'!F15=0,"-",'Raw Data'!F5/'Raw Data'!F15) -> 11.888889 | G5: =IF('Raw Data'!G15=0,"-",'Raw Data'!G5/'Raw Data'!G15) -> 10.486322 | H5: =IF('Raw Data'!H15=0,"-",'Raw Data'!H5/'Raw Data'!H15) -> 12.258953 | I5: =IF('Raw Data'!I15=0,"-",'Raw Data'!I5/'Raw Data'!I15) -> 11.928783 | J5: =AVERAGE(B5:I5) -> 12.042678 | K5: =MEDIAN(B5:I5) -> 12.093868 | L5: =MIN(B5:I5) -> 10.486322 | M5: =MAX(B5:I5) -> 12.929688 | N5: Price / EPS FY2024A
A6: P/E — FY2025E (x) | B6: =IF('Raw Data'!B16=0,"-",'Raw Data'!B5/'Raw Data'!B16) -> 11.162791 | C6: =IF('Raw Data'!C16=0,"-",'Raw Data'!C5/'Raw Data'!C16) -> 11.298701 | D6: =IF('Raw Data'!D16=0,"-",'Raw Data'!D5/'Raw Data'!D16) -> 11.413793 | E6: =IF('Raw Data'!E16=0,"-",'Raw Data'!E5/'Raw Data'!E16) -> 11.590909 | F6: =IF('Raw Data'!F16=0,"-",'Raw Data'!F5/'Raw Data'!F16) -> 10.918367 | G6: =IF('Raw Data'!G16=0,"-",'Raw Data'!G5/'Raw Data'!G16) -> 9.5833333 | H6: =IF('Raw Data'!H16=0,"-",'Raw Data'!H5/'Raw Data'!H16) -> 11.265823 | I6: =IF('Raw Data'!I16=0,"-",'Raw Data'!I5/'Raw Data'!I16) -> 11.013699 | J6: =AVERAGE(B6:I6) -> 11.030927 | K6: =MEDIAN(B6:I6) -> 11.214307 | L6: =MIN(B6:I6) -> 9.5833333 | M6: =MAX(B6:I6) -> 11.590909 | N6: Price / EPS FY2025E [Primary valuation metric for banks]
A7: P/E — FY2026E (x) | B7: =IF('Raw Data'!B17=0,"-",'Raw Data'!B5/'Raw Data'!B17) -> 10.335917 | C7: =IF('Raw Data'!C17=0,"-",'Raw Data'!C5/'Raw Data'!C17) -> 10.456731 | D7: =IF('Raw Data'!D17=0,"-",'Raw Data'!D5/'Raw Data'!D17) -> 10.57508 | E7: =IF('Raw Data'!E17=0,"-",'Raw Data'!E5/'Raw Data'!E17) -> 10.732323 | F7: =IF('Raw Data'!F17=0,"-",'Raw Data'!F5/'Raw Data'!F17) -> 10.113422 | G7: =IF('Raw Data'!G17=0,"-",'Raw Data'!G5/'Raw Data'!G17) -> 8.8688946 | H7: =IF('Raw Data'!H17=0,"-",'Raw Data'!H5/'Raw Data'!H17) -> 10.421546 | I7: =IF('Raw Data'!I17=0,"-",'Raw Data'!I5/'Raw Data'!I17) -> 10.203046 | J7: =AVERAGE(B7:I7) -> 10.21337 | K7: =MEDIAN(B7:I7) -> 10.378731 | L7: =MIN(B7:I7) -> 8.8688946 | M7: =MAX(B7:I7) -> 10.732323 | N7: Price / EPS FY2026E
A8: EPS Growth FY24A→25E (%) | B8: =IF('Raw Data'!B15=0,"-",'Raw Data'!B16/'Raw Data'!B15-1) -> 0.066997519 | C8: =IF('Raw Data'!C15=0,"-",'Raw Data'!C16/'Raw Data'!C15-1) -> 0.09375 | D8: =IF('Raw Data'!D15=0,"-",'Raw Data'!D16/'Raw Data'!D15-1) -> 0.1328125 | E8: =IF('Raw Data'!E15=0,"-",'Raw Data'!E16/'Raw Data'!E15-1) -> 0.085347805 | F8: =IF('Raw Data'!F15=0,"-",'Raw Data'!F16/'Raw Data'!F15-1) -> 0.088888889 | G8: =IF('Raw Data'!G15=0,"-",'Raw Data'!G16/'Raw Data'!G15-1) -> 0.094224924 | H8: =IF('Raw Data'!H15=0,"-",'Raw Data'!H16/'Raw Data'!H15-1) -> 0.08815427 | I8: =IF('Raw Data'!I15=0,"-",'Raw Data'!I16/'Raw Data'!I15-1) -> 0.083086053 | J8: =AVERAGE(B8:I8) -> 0.091657745 | K8: =MEDIAN(B8:I8) -> 0.088521579 | L8: =MIN(B8:I8) -> 0.066997519 | M8: =MAX(B8:I8) -> 0.1328125 | N8: 1-yr EPS growth rate — drives PEG
A10: BOOK VALUE MULTIPLES (Key for Banks)
A11: Price / Book Value (x) | B11: =IF('Raw Data'!B20=0,"-",'Raw Data'!B5/'Raw Data'!B20) -> 2.2119816 | C11: =IF('Raw Data'!C20=0,"-",'Raw Data'!C5/'Raw Data'!C20) -> 1.2645349 | D11: =IF('Raw Data'!D20=0,"-",'Raw Data'!D5/'Raw Data'!D20) -> 1.2350746 | E11: =IF('Raw Data'!E20=0,"-",'Raw Data'!E5/'Raw Data'!E20) -> 1.5310718 | F11: =IF('Raw Data'!F20=0,"-",'Raw Data'!F5/'Raw Data'!F20) -> 1.7147436 | G11: =IF('Raw Data'!G20=0,"-",'Raw Data'!G5/'Raw Data'!G20) -> 0.68316832 | H11: =IF('Raw Data'!H20=0,"-",'Raw Data'!H5/'Raw Data'!H20) -> 1.4126984 | I11: =IF('Raw Data'!I20=0,"-",'Raw Data'!I5/'Raw Data'!I20) -> 0.94588235 | J11: =AVERAGE(B11:I11) -> 1.3748944 | K11: =MEDIAN(B11:I11) -> 1.3386166 | L11: =MIN(B11:I11) -> 0.68316832 | M11: =MAX(B11:I11) -> 2.2119816 | N11: Price / BVPS FY2024A [Core bank valuation metric]
A12: Price / Tang. Book Value (x) | B12: =IF('Raw Data'!B21=0,"-",'Raw Data'!B5/'Raw Data'!B21) -> 2.5751073 | C12: =IF('Raw Data'!C21=0,"-",'Raw Data'!C5/'Raw Data'!C21) -> 1.7330677 | D12: =IF('Raw Data'!D21=0,"-",'Raw Data'!D5/'Raw Data'!D21) -> 1.6067961 | E12: =IF('Raw Data'!E21=0,"-",'Raw Data'!E5/'Raw Data'!E21) -> 1.632 | F12: =IF('Raw Data'!F21=0,"-",'Raw Data'!F5/'Raw Data'!F21) -> 2.0303605 | G12: =IF('Raw Data'!G21=0,"-",'Raw Data'!G5/'Raw Data'!G21) -> 0.7641196 | H12: =IF('Raw Data'!H21=0,"-",'Raw Data'!H5/'Raw Data'!H21) -> 1.8089431 | I12: =IF('Raw Data'!I21=0,"-",'Raw Data'!I5/'Raw Data'!I21) -> 1.3311258 | J12: =AVERAGE(B12:I12) -> 1.68519 | K12: =MEDIAN(B12:I12) -> 1.6825339 | L12: =MIN(B12:I12) -> 0.7641196 | M12: =MAX(B12:I12) -> 2.5751073 | N12: Price / TBVPS [Excludes goodwill — analysts prefer TBV]
A13: Dividend Yield (%) | B13: ='Raw Data'!B22/'Raw Data'!B5 -> 0.025 | C13: ='Raw Data'!C22/'Raw Data'!C5 -> 0.025057471 | D13: ='Raw Data'!D22/'Raw Data'!D5 -> 0.025075529 | E13: ='Raw Data'!E22/'Raw Data'!E5 -> 0.025 | F13: ='Raw Data'!F22/'Raw Data'!F5 -> 0.025046729 | G13: ='Raw Data'!G22/'Raw Data'!G5 -> 0.025072464 | H13: ='Raw Data'!H22/'Raw Data'!H5 -> 0.02494382 | I13: ='Raw Data'!I22/'Raw Data'!I5 -> 0.025124378 | J13: =AVERAGE(B13:I13) -> 0.025040049 | K13: =MEDIAN(B13:I13) -> 0.0250521 | L13: =MIN(B13:I13) -> 0.02494382 | M13: =MAX(B13:I13) -> 0.025124378 | N13: Dividends per Share / Share Price
A15: EV-BASED MULTIPLES (Less Common for Banks — Shown for Reference)
A16: EV / Net Revenue (x) | B16: =IF('Raw Data'!B13=0,"-",'Raw Data'!B10/'Raw Data'!B13) -> 1.3573315 | C16: =IF('Raw Data'!C13=0,"-",'Raw Data'!C10/'Raw Data'!C13) -> 2.1120435 | D16: =IF('Raw Data'!D13=0,"-",'Raw Data'!D10/'Raw Data'!D13) -> 2.1333801 | E16: =IF('Raw Data'!E13=0,"-",'Raw Data'!E10/'Raw Data'!E13) -> 3.3670958 | F16: =IF('Raw Data'!F13=0,"-",'Raw Data'!F10/'Raw Data'!F13) -> 3.19073 | G16: =IF('Raw Data'!G13=0,"-",'Raw Data'!G10/'Raw Data'!G13) -> 2.7912069 | H16: =IF('Raw Data'!H13=0,"-",'Raw Data'!H10/'Raw Data'!H13) -> 1.6335483 | I16: =IF('Raw Data'!I13=0,"-",'Raw Data'!I10/'Raw Data'!I13) -> 1.933519 | J16: =AVERAGE(B16:I16) -> 2.3148569 | K16: =MEDIAN(B16:I16) -> 2.1227118 | L16: =MIN(B16:I16) -> 1.3573315 | M16: =MAX(B16:I16) -> 3.3670958 | N16: EV / FY2024A Net Revenue [Not primary for banks — shown for reference]
A17: EV / Net Income (x) | B17: =IF('Raw Data'!B14=0,"-",'Raw Data'!B10/'Raw Data'!B14) -> 4.2020147 | C17: =IF('Raw Data'!C14=0,"-",'Raw Data'!C10/'Raw Data'!C14) -> 7.6788205 | D17: =IF('Raw Data'!D14=0,"-",'Raw Data'!D10/'Raw Data'!D14) -> 8.4801942 | E17: =IF('Raw Data'!E14=0,"-",'Raw Data'!E10/'Raw Data'!E14) -> 12.617649 | F17: =IF('Raw Data'!F14=0,"-",'Raw Data'!F10/'Raw Data'!F14) -> 14.225453 | G17: =IF('Raw Data'!G14=0,"-",'Raw Data'!G10/'Raw Data'!G14) -> 17.734003 | H17: =IF('Raw Data'!H14=0,"-",'Raw Data'!H10/'Raw Data'!H14) -> 7.7315553 | I17: =IF('Raw Data'!I14=0,"-",'Raw Data'!I10/'Raw Data'!I14) -> 8.1709381 | J17: =AVERAGE(B17:I17) -> 10.105079 | K17: =MEDIAN(B17:I17) -> 8.3255661 | L17: =MIN(B17:I17) -> 4.2020147 | M17: =MAX(B17:I17) -> 17.734003 | N17: EV / FY2024A Net Income
A19: PROFITABILITY SUMMARY (Cross-Referenced from Raw Data)
A20: ROATCE (%) | B20: ='Raw Data'!B26 -> 0.208 | C20: ='Raw Data'!C26 -> 0.128 | D20: ='Raw Data'!D26 -> 0.148 | E20: ='Raw Data'!E26 -> 0.133 | F20: ='Raw Data'!F26 -> 0.168 | G20: ='Raw Data'!G26 -> 0.075 | H20: ='Raw Data'!H26 -> 0.165 | I20: ='Raw Data'!I26 -> 0.14 | J20: =AVERAGE(B20:I20) -> 0.145625 | K20: =MEDIAN(B20:I20) -> 0.144 | L20: =MIN(B20:I20) -> 0.075 | M20: =MAX(B20:I20) -> 0.208
A21: Efficiency Ratio (%) [lower = better] | B21: ='Raw Data'!B27 -> 0.541 | C21: ='Raw Data'!C27 -> 0.648 | D21: ='Raw Data'!D27 -> 0.638 | E21: ='Raw Data'!E27 -> 0.604 | F21: ='Raw Data'!F27 -> 0.711 | G21: ='Raw Data'!G27 -> 0.672 | H21: ='Raw Data'!H27 -> 0.598 | I21: ='Raw Data'!I27 -> 0.622 | J21: =AVERAGE(B21:I21) -> 0.62925 | K21: =MEDIAN(B21:I21) -> 0.63 | L21: =MIN(B21:I21) -> 0.541 | M21: =MAX(B21:I21) -> 0.711
A22: Net Interest Margin (%) | B22: ='Raw Data'!B28 -> 0.0282 | C22: ='Raw Data'!C28 -> 0.0195 | D22: ='Raw Data'!D28 -> 0.0269 | E22: ='Raw Data'!E28 -> N/A | F22: ='Raw Data'!F28 -> N/A | G22: ='Raw Data'!G28 -> 0.0239 | H22: ='Raw Data'!H28 -> 0.0289 | I22: ='Raw Data'!I28 -> 0.0305 | J22: =AVERAGE(B22:I22) -> 0.026316667 | K22: =MEDIAN(B22:I22) -> 0.02755 | L22: =MIN(B22:I22) -> 0.0195 | M22: =MAX(B22:I22) -> 0.0305
A23: CET1 Capital Ratio (%) | B23: ='Raw Data'!B29 -> 0.155 | C23: ='Raw Data'!C29 -> 0.136 | D23: ='Raw Data'!D29 -> 0.118 | E23: ='Raw Data'!E29 -> 0.148 | F23: ='Raw Data'!F29 -> 0.155 | G23: ='Raw Data'!G29 -> 0.136 | H23: ='Raw Data'!H29 -> 0.104 | I23: ='Raw Data'!I29 -> 0.108 | J23: =AVERAGE(B23:I23) -> 0.1325 | K23: =MEDIAN(B23:I23) -> 0.136 | L23: =MIN(B23:I23) -> 0.104 | M23: =MAX(B23:I23) -> 0.155
A24: Yellow = Key valuation metrics for banks (Forward P/E and P/TBV)

Sheet Valuation Summary
A1: VALUATION SUMMARY — Implied Price Ranges by Methodology ($)
A3: Implied price ranges are derived by applying peer median and 25th/75th percentile multiples to each bank's FY2025E / FY2024A financials. Select a target company using the dropdown input below.
A5: Target Company Selection
A6: Target Ticker (from peer group): | B6: JPM | L6: Enter ticker: JPM, BAC, WFC, GS, MS, C, USB, or TFC
A8: Target Company Data (Pulled from Raw Data by Ticker)
A9: Ticker | B9: =B6 -> JPM
A10: Company Name | B10: =IFERROR(VLOOKUP(B6,$K$40:$L$47,2,0),"Unknown") -> JPMorgan Chase
A11: Current Share Price ($) | B11: =INDEX('Raw Data'!B5:I5,MATCH(B6,'Raw Data'!B3:I3,0)) -> 240
A12: EPS FY2025E ($) | B12: =INDEX('Raw Data'!B16:I16,MATCH(B6,'Raw Data'!B3:I3,0)) -> 21.5
A13: EPS FY2026E ($) | B13: =INDEX('Raw Data'!B17:I17,MATCH(B6,'Raw Data'!B3:I3,0)) -> 23.22
A14: Book Value per Share ($) | B14: =INDEX('Raw Data'!B20:I20,MATCH(B6,'Raw Data'!B3:I3,0)) -> 108.5
A15: Tang. Book Value/Share ($) | B15: =INDEX('Raw Data'!B21:I21,MATCH(B6,'Raw Data'!B3:I3,0)) -> 93.2
A17: Implied Share Price Range by Valuation Methodology
A18: Methodology | B18: Metric Applied | C18: Low Multiple (25th pct) | D18: Low Implied Price ($) | E18: Median Multiple | F18: Median Implied Price ($) | G18: High Multiple (75th pct) | H18: High Implied Price ($) | I18: Current Price ($) | J18: Prem/(Disc) vs Median | K18: Notes
A19: Forward P/E | B19: P/E vs FY2025E EPS | C19: =QUARTILE('Trading Multiples'!B6:I6,1) -> 10.989866 | D19: =C19*B12 -> 236.28211 | E19: =MEDIAN('Trading Multiples'!B6:I6) -> 11.214307 | F19: =E19*B12 -> 241.10759 | G19: =QUARTILE('Trading Multiples'!B6:I6,3) -> 11.327474 | H19: =G19*B12 -> 243.5407 | I19: =B11 -> 240 | J19: =IF(F19=0,0,B11/F19-1) -> -0.0045937787 | K19: Primary bank valuation methodology; most used by sell-side
A20: P/Tangible BV | B20: Price / TBV/Share | C20: =QUARTILE('Trading Multiples'!B12:I12,1) -> 1.5378785 | D20: =C20*B15 -> 143.33028 | E20: =MEDIAN('Trading Multiples'!B12:I12) -> 1.6825339 | F20: =E20*B15 -> 156.81216 | G20: =QUARTILE('Trading Multiples'!B12:I12,3) -> 1.8642974 | H20: =G20*B15 -> 173.75252 | I20: =B11 -> 240 | J20: =IF(F20=0,0,B11/F20-1) -> 0.53049359 | K20: Key metric — excludes goodwill; preferred by most bank analysts
A21: Price/Book | B21: Price / BVPS | C21: =QUARTILE('Trading Multiples'!B11:I11,1) -> 1.1627766 | D21: =C21*B14 -> 126.16126 | E21: =MEDIAN('Trading Multiples'!B11:I11) -> 1.3386166 | F21: =E21*B14 -> 145.23991 | G21: =QUARTILE('Trading Multiples'!B11:I11,3) -> 1.5769897 | H21: =G21*B14 -> 171.10338 | I21: =B11 -> 240 | J21: =IF(F21=0,0,B11/F21-1) -> 0.65243841 | K21: Includes goodwill; useful cross-check to P/TBV
A23: Yellow = Median implied price (central estimate). Green = 25th/75th percentile range.
A24: Note: Multiples exclude the target company itself to avoid self-referential bias.
K40: JPM | L40: JPMorgan Chase
K41: BAC | L41: Bank of America
K42: WFC | L42: Wells Fargo
K43: GS | L43: Goldman Sachs
K44: MS | L44: Morgan Stanley
K45: C | L45: Citigroup
K46: USB | L46: U.S. Bancorp
K47: TFC | L47: Truist Financial

Sheet Chart Data
A1: CHART DATA — ROATCE vs. P/TBV (Scatter Plot)
A3: Ticker | B3: Company | C3: ROATCE (%) — X Axis | D3: P/TBV (x) — Y Axis | E3: Forward P/E (x)
A4: JPM | B4: JPMorgan Chase | C4: ='Raw Data'!B26 -> 0.208 | D4: ='Trading Multiples'!B12 -> 2.5751073 | E4: ='Trading Multiples'!B6 -> 11.162791
A5: BAC | B5: Bank of America | C5: ='Raw Data'!C26 -> 0.128 | D5: ='Trading Multiples'!C12 -> 1.7330677 | E5: ='Trading Multiples'!C6 -> 11.298701
A6: WFC | B6: Wells Fargo | C6: ='Raw Data'!D26 -> 0.148 | D6: ='Trading Multiples'!D12 -> 1.6067961 | E6: ='Trading Multiples'!D6 -> 11.413793
A7: GS | B7: Goldman Sachs | C7: ='Raw Data'!E26 -> 0.133 | D7: ='Trading Multiples'!E12 -> 1.632 | E7: ='Trading Multiples'!E6 -> 11.590909
A8: MS | B8: Morgan Stanley | C8: ='Raw Data'!F26 -> 0.168 | D8: ='Trading Multiples'!F12 -> 2.0303605 | E8: ='Trading Multiples'!F6 -> 10.918367
A9: C | B9: Citigroup | C9: ='Raw Data'!G26 -> 0.075 | D9: ='Trading Multiples'!G12 -> 0.7641196 | E9: ='Trading Multiples'!G6 -> 9.5833333
A10: USB | B10: U.S. Bancorp | C10: ='Raw Data'!H26 -> 0.165 | D10: ='Trading Multiples'!H12 -> 1.8089431 | E10: ='Trading Multiples'!H6 -> 11.265823
A11: TFC | B11: Truist Financial | C11: ='Raw Data'!I26 -> 0.14 | D11: ='Trading Multiples'!I12 -> 1.3311258 | E11: ='Trading Multiples'!I6 -> 11.013699
A13: Key Insight
A14: Banks with higher ROATCE generally trade at higher P/TBV multiples. This ROATCE vs. P/TBV scatter is the most commonly used framework by bank analysts to identify relative value. Banks trading below the regression line may be undervalued vs. peers; those above may be overvalued.
