Workbook

Sheet Cover
A1: JOHNSON & JOHNSON (JNJ)
A7: Discounted Cash Flow (DCF) Analysis | Portfolio Financial Model | April 2026
B10: KEY MODEL OUTPUTS
B11: Current Share Price (Apr 2026) | D11: =Assumptions!B46 -> 0
B13: Implied Share Price (DCF) | D13: ='DCF Valuation'!B28 -> -4124.7253
B15: Implied Upside / (Downside) | D15: ='DCF Valuation'!B30 -> -27.272136
B17: WACC | D17: =Assumptions!B35 -> 28500
B19: Terminal Growth Rate | D19: =Assumptions!B38 -> 1200
B34: Color Legend
B35: Blue Text | C35: Hardcoded input / assumption
B36: Black Text | C36: Formula / calculated value
B37: Green Text | C37: Cross-sheet reference

Sheet Assumptions
A1: ASSUMPTIONS & MODEL INPUTS — Johnson & Johnson (JNJ)
A3: Assumption | B3: FY2025E | C3: FY2026E | D3: FY2027E | E3: FY2028E | F3: FY2029E
A4: A | Revenue Growth Assumptions
A5: Total Revenue Growth Rate (%) | B5: 0.055 | C5: 0.05 | D5: 0.045 | E5: 0.045 | F5: 0.04 | G5: Source: JNJ Consensus Estimates & Pipeline Analysis, Apr 2026
A7: B | Income Statement Margin Assumptions
A8: Gross Margin (%) | B8: 0.684 | C8: 0.686 | D8: 0.688 | E8: 0.69 | F8: 0.692
A9: Research & Development (% Rev) | B9: 0.17 | C9: 0.17 | D9: 0.168 | E9: 0.168 | F9: 0.165
A10: SG&A (% Revenue) | B10: 0.23 | C10: 0.228 | D10: 0.225 | E10: 0.223 | F10: 0.22
A11: D&A (% Revenue) | B11: 0.09 | C11: 0.09 | D11: 0.088 | E11: 0.088 | F11: 0.085
A12: Capital Expenditures (% Rev) | B12: 0.05 | C12: 0.05 | D12: 0.048 | E12: 0.048 | F12: 0.045
A13: Change in NWC (% Rev Δ) | B13: 0.01 | C13: 0.01 | D13: 0.01 | E13: 0.01 | F13: 0.01
A15: C | Other P&L Assumptions
A16: Net Interest Expense ($M) | B16: 400 | C16: 300 | D16: 200 | E16: 100 | F16: 0
A17: Effective Tax Rate (%) | B17: 0.17 | C17: =$B$17 -> 0.17 | D17: =$B$17 -> 0.17 | E17: =$B$17 -> 0.17 | F17: =$B$17 -> 0.17 | G17: Consistent with JNJ guidance; single rate applied to all projection years
A19: D | WACC Build (Capital Asset Pricing Model)
A20: Risk-Free Rate (10Y UST) | B20: 0.045 | G20: Source: US Treasury, Apr 2026
A21: Equity Risk Premium (ERP) | B21: 0.055 | G21: Source: Damodaran Implied ERP, Jan 2026
A22: Levered Beta | B22: 0.55 | G22: Source: Bloomberg 5Y Monthly Beta vs. S&P 500, Apr 2026
A23: Cost of Equity — CAPM [=Rf + β × ERP] | B23: =B20+B22*B21 -> 0.07525
A24: Pre-Tax Cost of Debt | B24: 0.035 | G24: JNJ AA-rated; reflects blended coupon on outstanding debt
A25: After-Tax Cost of Debt [=Kd × (1 − t)] | B25: =B24*(1-B17) -> 0.02905
A26: Equity Weight (% Total Capital) | B26: 0.92
A27: Debt Weight (% Total Capital) [=1 − Equity Wt.] | B27: =1-B26 -> 0.08
A28: WACC [= Ke×We + Kd×Wd] | B28: =B23*B26+B25*B27 -> 0.071554
A30: E | Terminal Value Assumptions
A31: Terminal Growth Rate (g) — Gordon Growth Model | B31: 0.025
A32: Exit EV/EBITDA Multiple (Cross-Check) | B32: 14
A34: F | Balance Sheet Data (for Equity Bridge)
A35: Total Debt ($M) | B35: 28500 | G35: Source: JNJ FY2024 10-K, Balance Sheet
A36: Cash & Equivalents ($M) | B36: 19800 | G36: Source: JNJ FY2024 10-K, Balance Sheet
A37: Net Debt ($M) [= Debt − Cash] | B37: =B35-B36 -> 8700
A38: Minority Interest ($M) | B38: 1200 | G38: Source: JNJ FY2024 10-K (Kenvue stake retained)
A39: Shares Outstanding (M) | B39: 2400 | G39: Source: JNJ FY2024 10-K, diluted share count
A40: Current Share Price ($) | B40: 157 | G40: Source: Market price, approx. Apr 2026

Sheet IS & FCF
A1: JOHNSON & JOHNSON (JNJ) — Income Statement & Free Cash Flow Build ($M)
A3: Figures in $M unless noted | B3: FY2022A | C3: FY2023A | D3: FY2024A | E3: FY2025E | F3: FY2026E | G3: FY2027E | H3: FY2028E | I3: FY2029E | J3: Notes / Sources
A4: INCOME STATEMENT
A5: Revenue | B5: 93775 | C5: 85159 | D5: 88821 | E5: =D5*(1+Assumptions!B5) -> 93706.155 | F5: =E5*(1+Assumptions!C5) -> 98391.463 | G5: =F5*(1+Assumptions!D5) -> 102819.08 | H5: =G5*(1+Assumptions!E5) -> 107445.94 | I5: =H5*(1+Assumptions!F5) -> 111743.77 | J5: Source: JNJ 10-K FY2022–FY2024; FY2023 reflects Kenvue spin-off (May 2023)
A6: (-) Cost of Products Sold | B6: 30107 | C6: 27084 | D6: 28090 | E6: =E5*(1-Assumptions!B8) -> 29611.145 | F6: =F5*(1-Assumptions!C8) -> 30894.919 | G6: =G5*(1-Assumptions!D8) -> 32079.553 | H6: =H5*(1-Assumptions!E8) -> 33308.241 | I6: =I5*(1-Assumptions!F8) -> 34417.083 | J6: Source: JNJ 10-K FY2022–FY2024
A7: Gross Profit | B7: =B5-B6 -> 63668 | C7: =C5-C6 -> 58075 | D7: =D5-D6 -> 60731 | E7: =E5-E6 -> 64095.01 | F7: =F5-F6 -> 67496.543 | G7: =G5-G6 -> 70739.526 | H7: =H5-H6 -> 74137.697 | I7: =I5-I6 -> 77326.692
A8: Gross Margin % | B8: =IF(B5=0,"-",B7/B5) -> 0.67894428 | C8: =IF(C5=0,"-",C7/C5) -> 0.68195963 | D8: =IF(D5=0,"-",D7/D5) -> 0.68374596 | E8: =IF(E5=0,"-",E7/E5) -> 0.684 | F8: =IF(F5=0,"-",F7/F5) -> 0.686 | G8: =IF(G5=0,"-",G7/G5) -> 0.688 | H8: =IF(H5=0,"-",H7/H5) -> 0.69 | I8: =IF(I5=0,"-",I7/I5) -> 0.692
A10: (-) Research & Development | B10: 14603 | C10: 14650 | D10: 15124 | E10: =E5*Assumptions!B9 -> 15930.046 | F10: =F5*Assumptions!C9 -> 16726.549 | G10: =G5*Assumptions!D9 -> 17273.605 | H10: =H5*Assumptions!E9 -> 18050.917 | I10: =I5*Assumptions!F9 -> 18437.723 | J10: Source: JNJ 10-K FY2022–FY2024
A11: (-) Selling, Marketing & Administrative | B11: 22084 | C11: 20132 | D11: 21000 | E11: =E5*Assumptions!B10 -> 21552.416 | F11: =F5*Assumptions!C10 -> 22433.254 | G11: =G5*Assumptions!D10 -> 23134.293 | H11: =H5*Assumptions!E10 -> 23960.444 | I11: =I5*Assumptions!F10 -> 24583.63 | J11: Source: JNJ 10-K FY2022–FY2024
A12: EBITDA | B12: =B7-B10-B11 -> 26981 | C12: =C7-C10-C11 -> 23293 | D12: =D7-D10-D11 -> 24607 | E12: =E7-E10-E11 -> 26612.548 | F12: =F7-F10-F11 -> 28336.741 | G12: =G7-G10-G11 -> 30331.628 | H12: =H7-H10-H11 -> 32126.335 | I12: =I7-I10-I11 -> 34305.339
A13: EBITDA Margin % | B13: =IF(B5=0,"-",B12/B5) -> 0.28772061 | C13: =IF(C5=0,"-",C12/C5) -> 0.27352364 | D13: =IF(D5=0,"-",D12/D5) -> 0.27704034 | E13: =IF(E5=0,"-",E12/E5) -> 0.284 | F13: =IF(F5=0,"-",F12/F5) -> 0.288 | G13: =IF(G5=0,"-",G12/G5) -> 0.295 | H13: =IF(H5=0,"-",H12/H5) -> 0.299 | I13: =IF(I5=0,"-",I12/I5) -> 0.307
A15: (-) Depreciation & Amortization | B15: 8200 | C15: 7800 | D15: 8100 | E15: =E5*Assumptions!B11 -> 8433.5539 | F15: =F5*Assumptions!C11 -> 8855.2316 | G15: =G5*Assumptions!D11 -> 9048.0789 | H15: =H5*Assumptions!E11 -> 9455.2425 | I15: =I5*Assumptions!F11 -> 9498.2208 | J15: Includes acquired intangible amortization; Source: JNJ 10-K FY2022–FY2024
A16: EBIT (Operating Income) | B16: =B12-B15 -> 18781 | C16: =C12-C15 -> 15493 | D16: =D12-D15 -> 16507 | E16: =E12-E15 -> 18178.994 | F16: =F12-F15 -> 19481.51 | G16: =G12-G15 -> 21283.549 | H16: =H12-H15 -> 22671.093 | I16: =I12-I15 -> 24807.118
A17: EBIT Margin % | B17: =IF(B5=0,"-",B16/B5) -> 0.20027726 | C17: =IF(C5=0,"-",C16/C5) -> 0.18193027 | D17: =IF(D5=0,"-",D16/D5) -> 0.18584569 | E17: =IF(E5=0,"-",E16/E5) -> 0.194 | F17: =IF(F5=0,"-",F16/F5) -> 0.198 | G17: =IF(G5=0,"-",G16/G5) -> 0.207 | H17: =IF(H5=0,"-",H16/H5) -> 0.211 | I17: =IF(I5=0,"-",I16/I5) -> 0.222
A19: (-) Net Interest Expense | B19: 800 | C19: 900 | D19: 1100 | E19: =Assumptions!B16 -> 400 | F19: =Assumptions!C16 -> 300 | G19: =Assumptions!D16 -> 200 | H19: =Assumptions!E16 -> 100 | I19: =Assumptions!F16 -> 0 | J19: Source: JNJ 10-K; projected per Assumptions tab
A20: Pre-Tax Income (EBT) | B20: =B16-B19 -> 17981 | C20: =C16-C19 -> 14593 | D20: =D16-D19 -> 15407 | E20: =E16-E19 -> 17778.994 | F20: =F16-F19 -> 19181.51 | G20: =G16-G19 -> 21083.549 | H20: =H16-H19 -> 22571.093 | I20: =I16-I19 -> 24807.118
A21: (-) Income Taxes | B21: 4960 | C21: 4549 | D21: 5094 | E21: =E20*Assumptions!$B$17 -> 3022.429 | F21: =F20*Assumptions!$B$17 -> 3260.8566 | G21: =G20*Assumptions!$B$17 -> 3584.2034 | H21: =H20*Assumptions!$B$17 -> 3837.0858 | I21: =I20*Assumptions!$B$17 -> 4217.2101
A22: Net Income | B22: =B20-B21 -> 13021 | C22: =C20-C21 -> 10044 | D22: =D20-D21 -> 10313 | E22: =E20-E21 -> 14756.565 | F22: =F20-F21 -> 15920.653 | G22: =G20-G21 -> 17499.346 | H22: =H20-H21 -> 18734.007 | I22: =I20-I21 -> 20589.908
A23: Net Margin % | B23: =IF(B5=0,"-",B22/B5) -> 0.13885364 | C23: =IF(C5=0,"-",C22/C5) -> 0.11794408 | D23: =IF(D5=0,"-",D22/D5) -> 0.11610993 | E23: =IF(E5=0,"-",E22/E5) -> 0.15747701 | F23: =IF(F5=0,"-",F22/F5) -> 0.16180929 | G23: =IF(G5=0,"-",G22/G5) -> 0.17019551 | H23: =IF(H5=0,"-",H22/H5) -> 0.17435752 | I23: =IF(I5=0,"-",I22/I5) -> 0.18426
A25: Diluted EPS ($) | B25: =B22/Assumptions!$B$39 -> 5.4254167 | C25: =C22/Assumptions!$B$39 -> 4.185 | D25: =D22/Assumptions!$B$39 -> 4.2970833 | E25: =E22/Assumptions!$B$39 -> 6.1485688 | F25: =F22/Assumptions!$B$39 -> 6.6336054 | G25: =G22/Assumptions!$B$39 -> 7.2913941 | H25: =H22/Assumptions!$B$39 -> 7.8058362 | I25: =I22/Assumptions!$B$39 -> 8.5791283
A28: FREE CASH FLOW BUILD — Unlevered FCF
A29: EBIT | B29: =B16 -> 18781 | C29: =C16 -> 15493 | D29: =D16 -> 16507 | E29: =E16 -> 18178.994 | F29: =F16 -> 19481.51 | G29: =G16 -> 21283.549 | H29: =H16 -> 22671.093 | I29: =I16 -> 24807.118
A30: (-) Cash Taxes on EBIT [EBIT × Tax Rate] | B30: =B29*Assumptions!$B$17 -> 3192.77 | C30: =C29*Assumptions!$B$17 -> 2633.81 | D30: =D29*Assumptions!$B$17 -> 2806.19 | E30: =E29*Assumptions!$B$17 -> 3090.429 | F30: =F29*Assumptions!$B$17 -> 3311.8566 | G30: =G29*Assumptions!$B$17 -> 3618.2034 | H30: =H29*Assumptions!$B$17 -> 3854.0858 | I30: =I29*Assumptions!$B$17 -> 4217.2101
A31: NOPAT [Net Operating Profit After Tax] | B31: =B29-B30 -> 15588.23 | C31: =C29-C30 -> 12859.19 | D31: =D29-D30 -> 13700.81 | E31: =E29-E30 -> 15088.565 | F31: =F29-F30 -> 16169.653 | G31: =G29-G30 -> 17665.346 | H31: =H29-H30 -> 18817.007 | I31: =I29-I30 -> 20589.908
A32: (+) Depreciation & Amortization | B32: =B15 -> 8200 | C32: =C15 -> 7800 | D32: =D15 -> 8100 | E32: =E15 -> 8433.5539 | F32: =F15 -> 8855.2316 | G32: =G15 -> 9048.0789 | H32: =H15 -> 9455.2425 | I32: =I15 -> 9498.2208
A33: (-) Capital Expenditures | B33: 4333 | C33: 4100 | D33: 4400 | E33: =E5*Assumptions!B12 -> 4685.3077 | F33: =F5*Assumptions!C12 -> 4919.5731 | G33: =G5*Assumptions!D12 -> 4935.3158 | H33: =H5*Assumptions!E12 -> 5157.405 | I33: =I5*Assumptions!F12 -> 5028.4699 | J33: Source: JNJ 10-K Cash Flow Statement FY2022–FY2024
A34: (-) Increase in Net Working Capital | B34: 1200 | C34: -800 | D34: 500 | E34: =(E5-D5)*Assumptions!B13 -> 48.85155 | F34: =(F5-E5)*Assumptions!C13 -> 46.853078 | G34: =(G5-F5)*Assumptions!D13 -> 44.276158 | H34: =(H5-G5)*Assumptions!E13 -> 46.268585 | I34: =(I5-H5)*Assumptions!F13 -> 42.978375 | J34: Positive = cash outflow (NWC increase); Source: JNJ 10-K FY2022–FY2024
A35: Unlevered Free Cash Flow (UFCF) | B35: =B31+B32-B33-B34 -> 18255.23 | C35: =C31+C32-C33-C34 -> 17359.19 | D35: =D31+D32-D33-D34 -> 16900.81 | E35: =E31+E32-E33-E34 -> 18787.96 | F35: =F31+F32-F33-F34 -> 20058.458 | G35: =G31+G32-G33-G34 -> 21733.833 | H35: =H31+H32-H33-H34 -> 23068.576 | I35: =I31+I32-I33-I34 -> 25016.681
A36: UFCF Margin % | B36: =IF(B5=0,"-",B35/B5) -> 0.19467054 | C36: =IF(C5=0,"-",C35/C5) -> 0.20384446 | D36: =IF(D5=0,"-",D35/D5) -> 0.19027944 | E36: =IF(E5=0,"-",E35/E5) -> 0.20049867 | F36: =IF(F5=0,"-",F35/F5) -> 0.20386381 | G36: =IF(G5=0,"-",G35/G5) -> 0.21137938 | H36: =IF(H5=0,"-",H35/H5) -> 0.21469938 | I36: =IF(I5=0,"-",I35/I5) -> 0.22387538

Sheet DCF Valuation
A1: JOHNSON & JOHNSON (JNJ) — DCF Valuation ($M, except per-share data)
A3: Key Valuation Assumptions
A4: WACC | B4: =Assumptions!B35 -> 28500 | D4: Terminal Growth Rate (g) | E4: =Assumptions!B38 -> 1200
A6: Projection Period Cash Flows
A7: Year | B7: FY2025E | C7: FY2026E | D7: FY2027E | E7: FY2028E | F7: FY2029E
A8: Unlevered Free Cash Flow ($M) | B8: ='IS & FCF'!E35 -> 18787.96 | C8: ='IS & FCF'!F35 -> 20058.458 | D8: ='IS & FCF'!G35 -> 21733.833 | E8: ='IS & FCF'!H35 -> 23068.576 | F8: ='IS & FCF'!I35 -> 25016.681
A9: Discount Period (End-of-Year Convention) | B9: 1 | C9: 2 | D9: 3 | E9: 4 | F9: 5
A10: Discount Factor [= 1 ÷ (1 + WACC)^t] | B10: =1/(1+Assumptions!$B$35)^B9 -> 3.5086488e-05 | C10: =1/(1+Assumptions!$B$35)^C9 -> 1.2310617e-09 | D10: =1/(1+Assumptions!$B$35)^D9 -> 4.319363e-14 | E10: =1/(1+Assumptions!$B$35)^E9 -> 1.5155128e-18 | F10: =1/(1+Assumptions!$B$35)^F9 -> 5.3174022e-23
A11: PV of UFCF [= UFCF × Discount Factor] | B11: =B8*B10 -> 0.65920353 | C11: =C8*C10 -> 2.4693199e-05 | D11: =D8*D10 -> 9.3876314e-10 | E11: =E8*E10 -> 3.4960722e-14 | F11: =F8*F10 -> 1.3302375e-18
A13: Terminal Value — Gordon Growth Model [TV = UFCF × (1+g) ÷ (WACC − g)]
A14: Terminal Year UFCF ($M) [FY2029E] | B14: ='IS & FCF'!I35 -> 25016.681
A15: Terminal Growth Rate (g) | B15: =Assumptions!B38 -> 1200
A16: WACC | B16: =Assumptions!B35 -> 28500
A17: Terminal Value ($M) [= UFCF×(1+g) ÷ (WACC−g)] | B17: =B14*(1+B15)/(B16-B15) -> 1100.5507
A18: PV of Terminal Value ($M) [= TV ÷ (1+WACC)^5] | B18: =B17/(1+Assumptions!B35)^5 -> 5.8520705e-20
A20: Enterprise Value → Equity Value Bridge
A21: Sum of PV(FCFs) — Projection Period | B21: =SUM(B11:F11) -> 0.65922822
A22: (+) PV of Terminal Value | B22: =B18 -> 5.8520705e-20
A23: Enterprise Value ($M) | B23: =B21+B22 -> 0.65922822
A24: (-) Net Debt ($M) | B24: =Assumptions!B37 -> 8700
A25: (-) Minority Interest ($M) | B25: =Assumptions!B38 -> 1200
A26: Equity Value ($M) | B26: =B23-B24-B25 -> -9899.3408
A27: Shares Outstanding (M) | B27: =Assumptions!B39 -> 2400
A28: ➤ Implied Share Price ($) | B28: =B26/B27*1000 -> -4124.7253 | H28: Equity Value ($M) ÷ Shares (M) × 1000 conversion factor (shares in M, EV in $M)
A29: Current Share Price ($) | B29: =Assumptions!B40 -> 157
A30: Implied Premium / (Discount) to Market | B30: =B28/B29-1 -> -27.272136
A32: Value Composition
A33: % of EV from Projection Period FCFs | B33: =B21/B23 -> 1
A34: % of EV from Terminal Value | B34: =B22/B23 -> 8.8771541e-20
A36: Exit Multiple Cross-Check (EV/EBITDA)
A37: EV from DCF ($M) | B37: =B23 -> 0.65922822
A38: FY2029E EBITDA ($M) | B38: ='IS & FCF'!I12 -> 34305.339
A39: Implied Exit EV/EBITDA Multiple | B39: =B37/B38 -> 1.9216491e-05
A40: Target Exit Multiple (from Assumptions) | B40: =Assumptions!B32 -> 14
A41: Cross-Check Implied Share Price ($) | B41: =(B38*Assumptions!B32-Assumptions!B37-Assumptions!B38)/Assumptions!B39*1000 -> 195989.48

Sheet Sensitivity Analysis
A1: SENSITIVITY ANALYSIS — Implied Share Price | WACC vs. Terminal Growth Rate
A3: Each cell shows the implied share price at the intersection of a given WACC (rows) and terminal growth rate (columns). Base case highlighted in yellow. All other assumptions held constant.
A5: Implied Share Price ($)
A6: WACC ↓ TGR → | B6: Base Case | C6: 0.015 | D6: 0.02 | E6: 0.025 | F6: 0.03 | G6: 0.035 | H6: 0.04
A7: 0.055 | B7: ↑ | C7: =IF($A7<=C$6,"N/A",('IS & FCF'!E35/(1+$A7)^1+'IS & FCF'!F35/(1+$A7)^2+'IS & FCF'!G35/(1+$A7)^3+'IS & FCF'!H35/(1+$A7)^4+'IS & FCF'!I35/(1+$A7)^5+('IS & FCF'!I35*(1+C$6)/($A7-C$6))/(1+$A7)^5-Assumptions!$B$37-Assumptions!$B$38)/Assumptions!$B$39*1000) -> 236628.05 | D7: =IF($A7<=D$6,"N/A",('IS & FCF'!E35/(1+$A7)^1+'IS & FCF'!F35/(1+$A7)^2+'IS & FCF'!G35/(1+$A7)^3+'IS & FCF'!H35/(1+$A7)^4+'IS & FCF'!I35/(1+$A7)^5+('IS & FCF'!I35*(1+D$6)/($A7-D$6))/(1+$A7)^5-Assumptions!$B$37-Assumptions!$B$38)/Assumptions!$B$39*1000) -> 266678.47 | E7: =IF($A7<=E$6,"N/A",('IS & FCF'!E35/(1+$A7)^1+'IS & FCF'!F35/(1+$A7)^2+'IS & FCF'!G35/(1+$A7)^3+'IS & FCF'!H35/(1+$A7)^4+'IS & FCF'!I35/(1+$A7)^5+('IS & FCF'!I35*(1+E$6)/($A7-E$6))/(1+$A7)^5-Assumptions!$B$37-Assumptions!$B$38)/Assumptions!$B$39*1000) -> 306745.7 | F7: =IF($A7<=F$6,"N/A",('IS & FCF'!E35/(1+$A7)^1+'IS & FCF'!F35/(1+$A7)^2+'IS & FCF'!G35/(1+$A7)^3+'IS & FCF'!H35/(1+$A7)^4+'IS & FCF'!I35/(1+$A7)^5+('IS & FCF'!I35*(1+F$6)/($A7-F$6))/(1+$A7)^5-Assumptions!$B$37-Assumptions!$B$38)/Assumptions!$B$39*1000) -> 362839.82 | G7: =IF($A7<=G$6,"N/A",('IS & FCF'!E35/(1+$A7)^1+'IS & FCF'!F35/(1+$A7)^2+'IS & FCF'!G35/(1+$A7)^3+'IS & FCF'!H35/(1+$A7)^4+'IS & FCF'!I35/(1+$A7)^5+('IS & FCF'!I35*(1+G$6)/($A7-G$6))/(1+$A7)^5-Assumptions!$B$37-Assumptions!$B$38)/Assumptions!$B$39*1000) -> 446981 | H7: =IF($A7<=H$6,"N/A",('IS & FCF'!E35/(1+$A7)^1+'IS & FCF'!F35/(1+$A7)^2+'IS & FCF'!G35/(1+$A7)^3+'IS & FCF'!H35/(1+$A7)^4+'IS & FCF'!I35/(1+$A7)^5+('IS & FCF'!I35*(1+H$6)/($A7-H$6))/(1+$A7)^5-Assumptions!$B$37-Assumptions!$B$38)/Assumptions!$B$39*1000) -> 587216.3
A8: 0.06 | B8: ↑ | C8: =IF($A8<=C$6,"N/A",('IS & FCF'!E35/(1+$A8)^1+'IS & FCF'!F35/(1+$A8)^2+'IS & FCF'!G35/(1+$A8)^3+'IS & FCF'!H35/(1+$A8)^4+'IS & FCF'!I35/(1+$A8)^5+('IS & FCF'!I35*(1+C$6)/($A8-C$6))/(1+$A8)^5-Assumptions!$B$37-Assumptions!$B$38)/Assumptions!$B$39*1000) -> 209392.8 | D8: =IF($A8<=D$6,"N/A",('IS & FCF'!E35/(1+$A8)^1+'IS & FCF'!F35/(1+$A8)^2+'IS & FCF'!G35/(1+$A8)^3+'IS & FCF'!H35/(1+$A8)^4+'IS & FCF'!I35/(1+$A8)^5+('IS & FCF'!I35*(1+D$6)/($A8-D$6))/(1+$A8)^5-Assumptions!$B$37-Assumptions!$B$38)/Assumptions!$B$39*1000) -> 232327.47 | E8: =IF($A8<=E$6,"N/A",('IS & FCF'!E35/(1+$A8)^1+'IS & FCF'!F35/(1+$A8)^2+'IS & FCF'!G35/(1+$A8)^3+'IS & FCF'!H35/(1+$A8)^4+'IS & FCF'!I35/(1+$A8)^5+('IS & FCF'!I35*(1+E$6)/($A8-E$6))/(1+$A8)^5-Assumptions!$B$37-Assumptions!$B$38)/Assumptions!$B$39*1000) -> 261814.9 | F8: =IF($A8<=F$6,"N/A",('IS & FCF'!E35/(1+$A8)^1+'IS & FCF'!F35/(1+$A8)^2+'IS & FCF'!G35/(1+$A8)^3+'IS & FCF'!H35/(1+$A8)^4+'IS & FCF'!I35/(1+$A8)^5+('IS & FCF'!I35*(1+F$6)/($A8-F$6))/(1+$A8)^5-Assumptions!$B$37-Assumptions!$B$38)/Assumptions!$B$39*1000) -> 301131.47 | G8: =IF($A8<=G$6,"N/A",('IS & FCF'!E35/(1+$A8)^1+'IS & FCF'!F35/(1+$A8)^2+'IS & FCF'!G35/(1+$A8)^3+'IS & FCF'!H35/(1+$A8)^4+'IS & FCF'!I35/(1+$A8)^5+('IS & FCF'!I35*(1+G$6)/($A8-G$6))/(1+$A8)^5-Assumptions!$B$37-Assumptions!$B$38)/Assumptions!$B$39*1000) -> 356174.68 | H8: =IF($A8<=H$6,"N/A",('IS & FCF'!E35/(1+$A8)^1+'IS & FCF'!F35/(1+$A8)^2+'IS & FCF'!G35/(1+$A8)^3+'IS & FCF'!H35/(1+$A8)^4+'IS & FCF'!I35/(1+$A8)^5+('IS & FCF'!I35*(1+H$6)/($A8-H$6))/(1+$A8)^5-Assumptions!$B$37-Assumptions!$B$38)/Assumptions!$B$39*1000) -> 438739.49
A9: 0.065 | B9: ↑ | C9: =IF($A9<=C$6,"N/A",('IS & FCF'!E35/(1+$A9)^1+'IS & FCF'!F35/(1+$A9)^2+'IS & FCF'!G35/(1+$A9)^3+'IS & FCF'!H35/(1+$A9)^4+'IS & FCF'!I35/(1+$A9)^5+('IS & FCF'!I35*(1+C$6)/($A9-C$6))/(1+$A9)^5-Assumptions!$B$37-Assumptions!$B$38)/Assumptions!$B$39*1000) -> 187612.89 | D9: =IF($A9<=D$6,"N/A",('IS & FCF'!E35/(1+$A9)^1+'IS & FCF'!F35/(1+$A9)^2+'IS & FCF'!G35/(1+$A9)^3+'IS & FCF'!H35/(1+$A9)^4+'IS & FCF'!I35/(1+$A9)^5+('IS & FCF'!I35*(1+D$6)/($A9-D$6))/(1+$A9)^5-Assumptions!$B$37-Assumptions!$B$38)/Assumptions!$B$39*1000) -> 205618.49 | E9: =IF($A9<=E$6,"N/A",('IS & FCF'!E35/(1+$A9)^1+'IS & FCF'!F35/(1+$A9)^2+'IS & FCF'!G35/(1+$A9)^3+'IS & FCF'!H35/(1+$A9)^4+'IS & FCF'!I35/(1+$A9)^5+('IS & FCF'!I35*(1+E$6)/($A9-E$6))/(1+$A9)^5-Assumptions!$B$37-Assumptions!$B$38)/Assumptions!$B$39*1000) -> 228125.48 | F9: =IF($A9<=F$6,"N/A",('IS & FCF'!E35/(1+$A9)^1+'IS & FCF'!F35/(1+$A9)^2+'IS & FCF'!G35/(1+$A9)^3+'IS & FCF'!H35/(1+$A9)^4+'IS & FCF'!I35/(1+$A9)^5+('IS & FCF'!I35*(1+F$6)/($A9-F$6))/(1+$A9)^5-Assumptions!$B$37-Assumptions!$B$38)/Assumptions!$B$39*1000) -> 257063.05 | G9: =IF($A9<=G$6,"N/A",('IS & FCF'!E35/(1+$A9)^1+'IS & FCF'!F35/(1+$A9)^2+'IS & FCF'!G35/(1+$A9)^3+'IS & FCF'!H35/(1+$A9)^4+'IS & FCF'!I35/(1+$A9)^5+('IS & FCF'!I35*(1+G$6)/($A9-G$6))/(1+$A9)^5-Assumptions!$B$37-Assumptions!$B$38)/Assumptions!$B$39*1000) -> 295646.47 | H9: =IF($A9<=H$6,"N/A",('IS & FCF'!E35/(1+$A9)^1+'IS & FCF'!F35/(1+$A9)^2+'IS & FCF'!G35/(1+$A9)^3+'IS & FCF'!H35/(1+$A9)^4+'IS & FCF'!I35/(1+$A9)^5+('IS & FCF'!I35*(1+H$6)/($A9-H$6))/(1+$A9)^5-Assumptions!$B$37-Assumptions!$B$38)/Assumptions!$B$39*1000) -> 349663.25
A10: 0.07 | B10: ↑ | C10: =IF($A10<=C$6,"N/A",('IS & FCF'!E35/(1+$A10)^1+'IS & FCF'!F35/(1+$A10)^2+'IS & FCF'!G35/(1+$A10)^3+'IS & FCF'!H35/(1+$A10)^4+'IS & FCF'!I35/(1+$A10)^5+('IS & FCF'!I35*(1+C$6)/($A10-C$6))/(1+$A10)^5-Assumptions!$B$37-Assumptions!$B$38)/Assumptions!$B$39*1000) -> 169800.33 | D10: =IF($A10<=D$6,"N/A",('IS & FCF'!E35/(1+$A10)^1+'IS & FCF'!F35/(1+$A10)^2+'IS & FCF'!G35/(1+$A10)^3+'IS & FCF'!H35/(1+$A10)^4+'IS & FCF'!I35/(1+$A10)^5+('IS & FCF'!I35*(1+D$6)/($A10-D$6))/(1+$A10)^5-Assumptions!$B$37-Assumptions!$B$38)/Assumptions!$B$39*1000) -> 184258.74 | E10: =IF($A10<=E$6,"N/A",('IS & FCF'!E35/(1+$A10)^1+'IS & FCF'!F35/(1+$A10)^2+'IS & FCF'!G35/(1+$A10)^3+'IS & FCF'!H35/(1+$A10)^4+'IS & FCF'!I35/(1+$A10)^5+('IS & FCF'!I35*(1+E$6)/($A10-E$6))/(1+$A10)^5-Assumptions!$B$37-Assumptions!$B$38)/Assumptions!$B$39*1000) -> 201930.14 | F10: =IF($A10<=F$6,"N/A",('IS & FCF'!E35/(1+$A10)^1+'IS & FCF'!F35/(1+$A10)^2+'IS & FCF'!G35/(1+$A10)^3+'IS & FCF'!H35/(1+$A10)^4+'IS & FCF'!I35/(1+$A10)^5+('IS & FCF'!I35*(1+F$6)/($A10-F$6))/(1+$A10)^5-Assumptions!$B$37-Assumptions!$B$38)/Assumptions!$B$39*1000) -> 224019.38 | G10: =IF($A10<=G$6,"N/A",('IS & FCF'!E35/(1+$A10)^1+'IS & FCF'!F35/(1+$A10)^2+'IS & FCF'!G35/(1+$A10)^3+'IS & FCF'!H35/(1+$A10)^4+'IS & FCF'!I35/(1+$A10)^5+('IS & FCF'!I35*(1+G$6)/($A10-G$6))/(1+$A10)^5-Assumptions!$B$37-Assumptions!$B$38)/Assumptions!$B$39*1000) -> 252419.83 | H10: =IF($A10<=H$6,"N/A",('IS & FCF'!E35/(1+$A10)^1+'IS & FCF'!F35/(1+$A10)^2+'IS & FCF'!G35/(1+$A10)^3+'IS & FCF'!H35/(1+$A10)^4+'IS & FCF'!I35/(1+$A10)^5+('IS & FCF'!I35*(1+H$6)/($A10-H$6))/(1+$A10)^5-Assumptions!$B$37-Assumptions!$B$38)/Assumptions!$B$39*1000) -> 290287.11
A11: 0.075 | B11: ↑ | C11: =IF($A11<=C$6,"N/A",('IS & FCF'!E35/(1+$A11)^1+'IS & FCF'!F35/(1+$A11)^2+'IS & FCF'!G35/(1+$A11)^3+'IS & FCF'!H35/(1+$A11)^4+'IS & FCF'!I35/(1+$A11)^5+('IS & FCF'!I35*(1+C$6)/($A11-C$6))/(1+$A11)^5-Assumptions!$B$37-Assumptions!$B$38)/Assumptions!$B$39*1000) -> 154963.1 | D11: =IF($A11<=D$6,"N/A",('IS & FCF'!E35/(1+$A11)^1+'IS & FCF'!F35/(1+$A11)^2+'IS & FCF'!G35/(1+$A11)^3+'IS & FCF'!H35/(1+$A11)^4+'IS & FCF'!I35/(1+$A11)^5+('IS & FCF'!I35*(1+D$6)/($A11-D$6))/(1+$A11)^5-Assumptions!$B$37-Assumptions!$B$38)/Assumptions!$B$39*1000) -> 166789.18 | E11: =IF($A11<=E$6,"N/A",('IS & FCF'!E35/(1+$A11)^1+'IS & FCF'!F35/(1+$A11)^2+'IS & FCF'!G35/(1+$A11)^3+'IS & FCF'!H35/(1+$A11)^4+'IS & FCF'!I35/(1+$A11)^5+('IS & FCF'!I35*(1+E$6)/($A11-E$6))/(1+$A11)^5-Assumptions!$B$37-Assumptions!$B$38)/Assumptions!$B$39*1000) -> 180980.47 | F11: =IF($A11<=F$6,"N/A",('IS & FCF'!E35/(1+$A11)^1+'IS & FCF'!F35/(1+$A11)^2+'IS & FCF'!G35/(1+$A11)^3+'IS & FCF'!H35/(1+$A11)^4+'IS & FCF'!I35/(1+$A11)^5+('IS & FCF'!I35*(1+F$6)/($A11-F$6))/(1+$A11)^5-Assumptions!$B$37-Assumptions!$B$38)/Assumptions!$B$39*1000) -> 198325.38 | G11: =IF($A11<=G$6,"N/A",('IS & FCF'!E35/(1+$A11)^1+'IS & FCF'!F35/(1+$A11)^2+'IS & FCF'!G35/(1+$A11)^3+'IS & FCF'!H35/(1+$A11)^4+'IS & FCF'!I35/(1+$A11)^5+('IS & FCF'!I35*(1+G$6)/($A11-G$6))/(1+$A11)^5-Assumptions!$B$37-Assumptions!$B$38)/Assumptions!$B$39*1000) -> 220006.52 | H11: =IF($A11<=H$6,"N/A",('IS & FCF'!E35/(1+$A11)^1+'IS & FCF'!F35/(1+$A11)^2+'IS & FCF'!G35/(1+$A11)^3+'IS & FCF'!H35/(1+$A11)^4+'IS & FCF'!I35/(1+$A11)^5+('IS & FCF'!I35*(1+H$6)/($A11-H$6))/(1+$A11)^5-Assumptions!$B$37-Assumptions!$B$38)/Assumptions!$B$39*1000) -> 247882.27
A12: 0.08 | B12: ↑ | C12: =IF($A12<=C$6,"N/A",('IS & FCF'!E35/(1+$A12)^1+'IS & FCF'!F35/(1+$A12)^2+'IS & FCF'!G35/(1+$A12)^3+'IS & FCF'!H35/(1+$A12)^4+'IS & FCF'!I35/(1+$A12)^5+('IS & FCF'!I35*(1+C$6)/($A12-C$6))/(1+$A12)^5-Assumptions!$B$37-Assumptions!$B$38)/Assumptions!$B$39*1000) -> 142414.45 | D12: =IF($A12<=D$6,"N/A",('IS & FCF'!E35/(1+$A12)^1+'IS & FCF'!F35/(1+$A12)^2+'IS & FCF'!G35/(1+$A12)^3+'IS & FCF'!H35/(1+$A12)^4+'IS & FCF'!I35/(1+$A12)^5+('IS & FCF'!I35*(1+D$6)/($A12-D$6))/(1+$A12)^5-Assumptions!$B$37-Assumptions!$B$38)/Assumptions!$B$39*1000) -> 152237.1 | E12: =IF($A12<=E$6,"N/A",('IS & FCF'!E35/(1+$A12)^1+'IS & FCF'!F35/(1+$A12)^2+'IS & FCF'!G35/(1+$A12)^3+'IS & FCF'!H35/(1+$A12)^4+'IS & FCF'!I35/(1+$A12)^5+('IS & FCF'!I35*(1+E$6)/($A12-E$6))/(1+$A12)^5-Assumptions!$B$37-Assumptions!$B$38)/Assumptions!$B$39*1000) -> 163845.69 | F12: =IF($A12<=F$6,"N/A",('IS & FCF'!E35/(1+$A12)^1+'IS & FCF'!F35/(1+$A12)^2+'IS & FCF'!G35/(1+$A12)^3+'IS & FCF'!H35/(1+$A12)^4+'IS & FCF'!I35/(1+$A12)^5+('IS & FCF'!I35*(1+F$6)/($A12-F$6))/(1+$A12)^5-Assumptions!$B$37-Assumptions!$B$38)/Assumptions!$B$39*1000) -> 177776 | G12: =IF($A12<=G$6,"N/A",('IS & FCF'!E35/(1+$A12)^1+'IS & FCF'!F35/(1+$A12)^2+'IS & FCF'!G35/(1+$A12)^3+'IS & FCF'!H35/(1+$A12)^4+'IS & FCF'!I35/(1+$A12)^5+('IS & FCF'!I35*(1+G$6)/($A12-G$6))/(1+$A12)^5-Assumptions!$B$37-Assumptions!$B$38)/Assumptions!$B$39*1000) -> 194801.93 | H12: =IF($A12<=H$6,"N/A",('IS & FCF'!E35/(1+$A12)^1+'IS & FCF'!F35/(1+$A12)^2+'IS & FCF'!G35/(1+$A12)^3+'IS & FCF'!H35/(1+$A12)^4+'IS & FCF'!I35/(1+$A12)^5+('IS & FCF'!I35*(1+H$6)/($A12-H$6))/(1+$A12)^5-Assumptions!$B$37-Assumptions!$B$38)/Assumptions!$B$39*1000) -> 216084.35
A13: 0.085 | B13: ↑ | C13: =IF($A13<=C$6,"N/A",('IS & FCF'!E35/(1+$A13)^1+'IS & FCF'!F35/(1+$A13)^2+'IS & FCF'!G35/(1+$A13)^3+'IS & FCF'!H35/(1+$A13)^4+'IS & FCF'!I35/(1+$A13)^5+('IS & FCF'!I35*(1+C$6)/($A13-C$6))/(1+$A13)^5-Assumptions!$B$37-Assumptions!$B$38)/Assumptions!$B$39*1000) -> 131663.83 | D13: =IF($A13<=D$6,"N/A",('IS & FCF'!E35/(1+$A13)^1+'IS & FCF'!F35/(1+$A13)^2+'IS & FCF'!G35/(1+$A13)^3+'IS & FCF'!H35/(1+$A13)^4+'IS & FCF'!I35/(1+$A13)^5+('IS & FCF'!I35*(1+D$6)/($A13-D$6))/(1+$A13)^5-Assumptions!$B$37-Assumptions!$B$38)/Assumptions!$B$39*1000) -> 139929.12 | E13: =IF($A13<=E$6,"N/A",('IS & FCF'!E35/(1+$A13)^1+'IS & FCF'!F35/(1+$A13)^2+'IS & FCF'!G35/(1+$A13)^3+'IS & FCF'!H35/(1+$A13)^4+'IS & FCF'!I35/(1+$A13)^5+('IS & FCF'!I35*(1+E$6)/($A13-E$6))/(1+$A13)^5-Assumptions!$B$37-Assumptions!$B$38)/Assumptions!$B$39*1000) -> 149571.96 | F13: =IF($A13<=F$6,"N/A",('IS & FCF'!E35/(1+$A13)^1+'IS & FCF'!F35/(1+$A13)^2+'IS & FCF'!G35/(1+$A13)^3+'IS & FCF'!H35/(1+$A13)^4+'IS & FCF'!I35/(1+$A13)^5+('IS & FCF'!I35*(1+F$6)/($A13-F$6))/(1+$A13)^5-Assumptions!$B$37-Assumptions!$B$38)/Assumptions!$B$39*1000) -> 160968.04 | G13: =IF($A13<=G$6,"N/A",('IS & FCF'!E35/(1+$A13)^1+'IS & FCF'!F35/(1+$A13)^2+'IS & FCF'!G35/(1+$A13)^3+'IS & FCF'!H35/(1+$A13)^4+'IS & FCF'!I35/(1+$A13)^5+('IS & FCF'!I35*(1+G$6)/($A13-G$6))/(1+$A13)^5-Assumptions!$B$37-Assumptions!$B$38)/Assumptions!$B$39*1000) -> 174643.34 | H13: =IF($A13<=H$6,"N/A",('IS & FCF'!E35/(1+$A13)^1+'IS & FCF'!F35/(1+$A13)^2+'IS & FCF'!G35/(1+$A13)^3+'IS & FCF'!H35/(1+$A13)^4+'IS & FCF'!I35/(1+$A13)^5+('IS & FCF'!I35*(1+H$6)/($A13-H$6))/(1+$A13)^5-Assumptions!$B$37-Assumptions!$B$38)/Assumptions!$B$39*1000) -> 191357.59
A14: 0.09 | B14: ↑ | C14: =IF($A14<=C$6,"N/A",('IS & FCF'!E35/(1+$A14)^1+'IS & FCF'!F35/(1+$A14)^2+'IS & FCF'!G35/(1+$A14)^3+'IS & FCF'!H35/(1+$A14)^4+'IS & FCF'!I35/(1+$A14)^5+('IS & FCF'!I35*(1+C$6)/($A14-C$6))/(1+$A14)^5-Assumptions!$B$37-Assumptions!$B$38)/Assumptions!$B$39*1000) -> 122351.51 | D14: =IF($A14<=D$6,"N/A",('IS & FCF'!E35/(1+$A14)^1+'IS & FCF'!F35/(1+$A14)^2+'IS & FCF'!G35/(1+$A14)^3+'IS & FCF'!H35/(1+$A14)^4+'IS & FCF'!I35/(1+$A14)^5+('IS & FCF'!I35*(1+D$6)/($A14-D$6))/(1+$A14)^5-Assumptions!$B$37-Assumptions!$B$38)/Assumptions!$B$39*1000) -> 129384.23 | E14: =IF($A14<=E$6,"N/A",('IS & FCF'!E35/(1+$A14)^1+'IS & FCF'!F35/(1+$A14)^2+'IS & FCF'!G35/(1+$A14)^3+'IS & FCF'!H35/(1+$A14)^4+'IS & FCF'!I35/(1+$A14)^5+('IS & FCF'!I35*(1+E$6)/($A14-E$6))/(1+$A14)^5-Assumptions!$B$37-Assumptions!$B$38)/Assumptions!$B$39*1000) -> 137498.9 | F14: =IF($A14<=F$6,"N/A",('IS & FCF'!E35/(1+$A14)^1+'IS & FCF'!F35/(1+$A14)^2+'IS & FCF'!G35/(1+$A14)^3+'IS & FCF'!H35/(1+$A14)^4+'IS & FCF'!I35/(1+$A14)^5+('IS & FCF'!I35*(1+F$6)/($A14-F$6))/(1+$A14)^5-Assumptions!$B$37-Assumptions!$B$38)/Assumptions!$B$39*1000) -> 146966.02 | G14: =IF($A14<=G$6,"N/A",('IS & FCF'!E35/(1+$A14)^1+'IS & FCF'!F35/(1+$A14)^2+'IS & FCF'!G35/(1+$A14)^3+'IS & FCF'!H35/(1+$A14)^4+'IS & FCF'!I35/(1+$A14)^5+('IS & FCF'!I35*(1+G$6)/($A14-G$6))/(1+$A14)^5-Assumptions!$B$37-Assumptions!$B$38)/Assumptions!$B$39*1000) -> 158154.43 | H14: =IF($A14<=H$6,"N/A",('IS & FCF'!E35/(1+$A14)^1+'IS & FCF'!F35/(1+$A14)^2+'IS & FCF'!G35/(1+$A14)^3+'IS & FCF'!H35/(1+$A14)^4+'IS & FCF'!I35/(1+$A14)^5+('IS & FCF'!I35*(1+H$6)/($A14-H$6))/(1+$A14)^5-Assumptions!$B$37-Assumptions!$B$38)/Assumptions!$B$39*1000) -> 171580.53
A15: 0.095 | B15: ↑ | C15: =IF($A15<=C$6,"N/A",('IS & FCF'!E35/(1+$A15)^1+'IS & FCF'!F35/(1+$A15)^2+'IS & FCF'!G35/(1+$A15)^3+'IS & FCF'!H35/(1+$A15)^4+'IS & FCF'!I35/(1+$A15)^5+('IS & FCF'!I35*(1+C$6)/($A15-C$6))/(1+$A15)^5-Assumptions!$B$37-Assumptions!$B$38)/Assumptions!$B$39*1000) -> 114207.71 | D15: =IF($A15<=D$6,"N/A",('IS & FCF'!E35/(1+$A15)^1+'IS & FCF'!F35/(1+$A15)^2+'IS & FCF'!G35/(1+$A15)^3+'IS & FCF'!H35/(1+$A15)^4+'IS & FCF'!I35/(1+$A15)^5+('IS & FCF'!I35*(1+D$6)/($A15-D$6))/(1+$A15)^5-Assumptions!$B$37-Assumptions!$B$38)/Assumptions!$B$39*1000) -> 120249.71 | E15: =IF($A15<=E$6,"N/A",('IS & FCF'!E35/(1+$A15)^1+'IS & FCF'!F35/(1+$A15)^2+'IS & FCF'!G35/(1+$A15)^3+'IS & FCF'!H35/(1+$A15)^4+'IS & FCF'!I35/(1+$A15)^5+('IS & FCF'!I35*(1+E$6)/($A15-E$6))/(1+$A15)^5-Assumptions!$B$37-Assumptions!$B$38)/Assumptions!$B$39*1000) -> 127154.85 | F15: =IF($A15<=F$6,"N/A",('IS & FCF'!E35/(1+$A15)^1+'IS & FCF'!F35/(1+$A15)^2+'IS & FCF'!G35/(1+$A15)^3+'IS & FCF'!H35/(1+$A15)^4+'IS & FCF'!I35/(1+$A15)^5+('IS & FCF'!I35*(1+F$6)/($A15-F$6))/(1+$A15)^5-Assumptions!$B$37-Assumptions!$B$38)/Assumptions!$B$39*1000) -> 135122.32 | G15: =IF($A15<=G$6,"N/A",('IS & FCF'!E35/(1+$A15)^1+'IS & FCF'!F35/(1+$A15)^2+'IS & FCF'!G35/(1+$A15)^3+'IS & FCF'!H35/(1+$A15)^4+'IS & FCF'!I35/(1+$A15)^5+('IS & FCF'!I35*(1+G$6)/($A15-G$6))/(1+$A15)^5-Assumptions!$B$37-Assumptions!$B$38)/Assumptions!$B$39*1000) -> 144417.71 | H15: =IF($A15<=H$6,"N/A",('IS & FCF'!E35/(1+$A15)^1+'IS & FCF'!F35/(1+$A15)^2+'IS & FCF'!G35/(1+$A15)^3+'IS & FCF'!H35/(1+$A15)^4+'IS & FCF'!I35/(1+$A15)^5+('IS & FCF'!I35*(1+H$6)/($A15-H$6))/(1+$A15)^5-Assumptions!$B$37-Assumptions!$B$38)/Assumptions!$B$39*1000) -> 155403.16
A16: 0.1 | B16: ↑ | C16: =IF($A16<=C$6,"N/A",('IS & FCF'!E35/(1+$A16)^1+'IS & FCF'!F35/(1+$A16)^2+'IS & FCF'!G35/(1+$A16)^3+'IS & FCF'!H35/(1+$A16)^4+'IS & FCF'!I35/(1+$A16)^5+('IS & FCF'!I35*(1+C$6)/($A16-C$6))/(1+$A16)^5-Assumptions!$B$37-Assumptions!$B$38)/Assumptions!$B$39*1000) -> 107026.1 | D16: =IF($A16<=D$6,"N/A",('IS & FCF'!E35/(1+$A16)^1+'IS & FCF'!F35/(1+$A16)^2+'IS & FCF'!G35/(1+$A16)^3+'IS & FCF'!H35/(1+$A16)^4+'IS & FCF'!I35/(1+$A16)^5+('IS & FCF'!I35*(1+D$6)/($A16-D$6))/(1+$A16)^5-Assumptions!$B$37-Assumptions!$B$38)/Assumptions!$B$39*1000) -> 112261.01 | E16: =IF($A16<=E$6,"N/A",('IS & FCF'!E35/(1+$A16)^1+'IS & FCF'!F35/(1+$A16)^2+'IS & FCF'!G35/(1+$A16)^3+'IS & FCF'!H35/(1+$A16)^4+'IS & FCF'!I35/(1+$A16)^5+('IS & FCF'!I35*(1+E$6)/($A16-E$6))/(1+$A16)^5-Assumptions!$B$37-Assumptions!$B$38)/Assumptions!$B$39*1000) -> 118193.9 | F16: =IF($A16<=F$6,"N/A",('IS & FCF'!E35/(1+$A16)^1+'IS & FCF'!F35/(1+$A16)^2+'IS & FCF'!G35/(1+$A16)^3+'IS & FCF'!H35/(1+$A16)^4+'IS & FCF'!I35/(1+$A16)^5+('IS & FCF'!I35*(1+F$6)/($A16-F$6))/(1+$A16)^5-Assumptions!$B$37-Assumptions!$B$38)/Assumptions!$B$39*1000) -> 124974.35 | G16: =IF($A16<=G$6,"N/A",('IS & FCF'!E35/(1+$A16)^1+'IS & FCF'!F35/(1+$A16)^2+'IS & FCF'!G35/(1+$A16)^3+'IS & FCF'!H35/(1+$A16)^4+'IS & FCF'!I35/(1+$A16)^5+('IS & FCF'!I35*(1+G$6)/($A16-G$6))/(1+$A16)^5-Assumptions!$B$37-Assumptions!$B$38)/Assumptions!$B$39*1000) -> 132797.94 | H16: =IF($A16<=H$6,"N/A",('IS & FCF'!E35/(1+$A16)^1+'IS & FCF'!F35/(1+$A16)^2+'IS & FCF'!G35/(1+$A16)^3+'IS & FCF'!H35/(1+$A16)^4+'IS & FCF'!I35/(1+$A16)^5+('IS & FCF'!I35*(1+H$6)/($A16-H$6))/(1+$A16)^5-Assumptions!$B$37-Assumptions!$B$38)/Assumptions!$B$39*1000) -> 141925.47
A18: Yellow = Base Case (WACC ≈ 7.2%, TGR = 2.5%)
A20: Reference — Current Model Key Outputs
A21: Base Case WACC | B21: =Assumptions!B35 -> 28500
A22: Base Case TGR | B22: =Assumptions!B38 -> 1200
A23: Sum of PV(FCFs) ($M) | B23: ='DCF Valuation'!B21 -> 0.65922822
A24: PV of Terminal Value ($M) | B24: ='DCF Valuation'!B22 -> 5.8520705e-20
A25: Enterprise Value ($M) | B25: ='DCF Valuation'!B23 -> 0.65922822
A26: Implied Share Price ($) | B26: ='DCF Valuation'!B28 -> -4124.7253
A27: Current Share Price ($) | B27: =Assumptions!B40 -> 157
A28: Implied Upside / (Down.) | B28: ='DCF Valuation'!B30 -> -27.272136
