Workbook

Sheet Cover
A1: JPMORGAN CHASE ACQUIRES CHARLES SCHWAB CORP.
A7: Merger & Acquisition (M&A) Model | Hypothetical Strategic Acquisition | Portfolio Model | April 2026
B9: TRANSACTION SUMMARY
B10: Acquirer | D10: JPMorgan Chase & Co. (JPM)
B11: Target | D11: The Charles Schwab Corp. (SCHW)
B12: Deal Structure | D12: Stock + Cash (Mixed Consideration)
B13: Offer Price per SCHW Share | D13: ='Deal Terms'!B7 -> 92.5
B14: Premium to SCHW Market Price | D14: ='Deal Terms'!B9 -> 0.25
B15: Transaction Value ($M) | D15: ='Deal Terms'!B12 -> 166.5
B16: Pro Forma EPS Accretion / (Dilution) | D16: ='Accretion Dilution'!B32 -> -0.040093109
B17: Deal Type | D17: Accretive
B32: Hypothetical transaction for portfolio purposes only. Not a recommendation or prediction. JPM and SCHW are independent companies. Financial data from public filings (FY2024/FY2025E).

Sheet Deal Terms
A1: DEAL TERMS & TRANSACTION STRUCTURE — JPM / SCHW ($M except per-share)
A3: A | Target (Schwab) Standalone Data
A4: SCHW Share Price (Pre-Announcement) | B4: 74 | C4: Market price approx. Apr 2026
A5: SCHW Shares Outstanding (M) | B5: 1800 | C5: Source: SCHW FY2024 10-K, diluted
A6: SCHW Market Cap ($M) | B6: =B4*B5/1000 -> 133.2 | C6: Calc: Share Price x Shares
A7: Offer Price per SCHW Share | B7: 92.5 | C7: ~25% premium to pre-announcement price
A8: Transaction Value ($M) | B8: =B7*B5/1000 -> 166.5 | C8: Calc: Offer Price x Shares
A9: Acquisition Premium | B9: =B7/B4-1 -> 0.25 | C9: Calc: Offer Price / Market Price - 1
A10: SCHW LTM Revenue ($M) | B10: 19745 | C10: Source: SCHW FY2024 10-K
A11: SCHW LTM Net Income ($M) | B11: 5591 | C11: Source: SCHW FY2024 10-K
A12: Transaction Value ($M) [check] | B12: =B8 -> 166.5 | C12: Cross-check
A13: Price / LTM Earnings (P/E) | B13: =IF(B11=0,0,(B8/B11)) -> 0.029780004 | C13: Transaction P/E
A14: Price / Book Value | B14: 2.8 | C14: Estimated P/BV at deal terms; Source: analyst consensus
A16: B | Consideration Mix & Financing
A17: Cash Consideration (% of Deal Value) | B17: 0.3 | C17: 30% cash / 70% stock; limits JPM dilution
A18: Stock Consideration (% of Deal Value) | B18: =1-B17 -> 0.7 | C18: Calc: 1 minus Cash pct
A19: Cash Funded by | B19: Debt + Excess Capital | C19: Combination of new debt and JPM surplus capital
A20: Cash Portion of Deal ($M) | B20: =B8*B17 -> 49.95 | C20: Calc: Deal Value x Cash pct
A21: Stock Portion of Deal ($M) | B21: =B8*B18 -> 116.55 | C21: Calc: Deal Value x Stock pct
A22: JPM Share Price (at announcement) | B22: 240 | C22: Approx. JPM price, Apr 2026
A23: Exchange Ratio [= Offer / JPM Price × Stock%] | B23: =B7/B22*B18 -> 0.26979167 | C23: New JPM shares per SCHW share
A24: New JPM Shares Issued (M) | B24: =B5*B23 -> 485.625 | C24: Calc: SCHW Shares x Exchange Ratio
A25: JPM Shares Outstanding (M, pre-deal) | B25: 2850 | C25: Source: JPM FY2024 10-K
A26: JPM Shares Outstanding (M, pro forma) | B26: =B25+B24 -> 3335.625 | C26: Calc: Pre-deal plus New shares
A27: % Dilution to JPM Shareholders | B27: =B24/B25 -> 0.17039474 | C27: Calc: New Shares div Pre-deal Shares
A29: C | Transaction Fees & Adjustments
A30: M&A Advisory Fees (% of TV) | B30: 0.005 | C30: ~0.5% for mega-cap deal
A31: Legal & Other Fees ($M) | B31: 250 | C31: Fixed estimate for regulatory complexity
A32: Financing Fees (% of Cash Used) | B32: 0.02 | C32: Debt issuance costs
A33: Total Transaction Fees ($M) | B33: =B8*B30+B31+B20*B32 -> 251.8315 | C33: Sum of advisory + legal + financing
A34: Goodwill Created ($M) | B34: =MAX(0,B8+B33-B35) -> 0 | C34: Calc: TV plus Fees minus Book Value
A35: SCHW Book Value ($M, approx.) | B35: 36000 | C35: Source: SCHW FY2024 10-K equity

Sheet Standalone Financials
A1: STANDALONE FINANCIALS — Acquirer (JPM) & Target (SCHW) ($M)
A3: Line Item | B3: JPM (FY2024A) | C3: JPM (FY2025E) | D3: SCHW (FY2024A) | E3: SCHW (FY2025E) | F3: Notes / Source
A4: INCOME STATEMENT (KEY ITEMS)
A5: Net Revenue / Net Interest Income + Fees ($M) | B5: 181014 | C5: 191000 | D5: 19745 | E5: 21200 | F5: JPM: Total net revenue FY2024; SCHW: Net revenues FY2024. Source: 10-K
A6: Provision for Credit Losses ($M) | B6: 9280 | C6: 9500 | D6: 0 | E6: 0 | F6: JPM: FY2024 PCL; SCHW: Minimal credit losses (brokerage model)
A7: Non-Interest Expense ($M) | B7: 87012 | C7: 90000 | D7: 12393 | E7: 13200 | F7: JPM/SCHW: Operating expenses. Source: 10-K FY2024
A8: Pre-Tax Income ($M) | B8: =B5-B6-B7 -> 84722 | C8: =C5-C6-C7 -> 91500 | D8: =D5-D6-D7 -> 7352 | E8: =E5-E6-E7 -> 8000 | F8: Calc: Revenue minus PCL minus Expense
A9: Income Tax Rate (%) | B9: 0.213 | C9: 0.213 | D9: 0.21 | E9: 0.21 | F9: Effective tax rates; Source: 10-K FY2024
A10: Net Income ($M) | B10: =B8*(1-B9) -> 66676.214 | C10: =C8*(1-C9) -> 72010.5 | D10: =D8*(1-D9) -> 5808.08 | E10: =E8*(1-E9) -> 6320 | F10: Calc: Pre-Tax Income x (1 - Tax Rate)
A11: Diluted EPS ($) | B11: =B10/2900*1000 -> 22991.798 | C11: =C10/2850*1000 -> 25266.842 | D11: =D10/1800*1000 -> 3226.7111 | E11: =E10/1800*1000 -> 3511.1111 | F11: Calc: Net Income div Diluted Shares
A13: KEY FINANCIAL METRICS
A14: Net Income ($M) | B14: =B10 -> 66676.214 | C14: =C10 -> 72010.5 | D14: =D10 -> 5808.08 | E14: =E10 -> 6320
A15: Diluted Shares (M) | B15: 2900 | C15: 2850 | D15: 1800 | E15: 1800
A16: Diluted EPS ($) | B16: =B11 -> 22991.798 | C16: =C11 -> 25266.842 | D16: =D11 -> 3226.7111 | E16: =E11 -> 3511.1111
A17: Return on Equity (%) | B17: 0.172 | C17: 0.18 | D17: 0.155 | E17: 0.165
A18: Efficiency Ratio (%) | B18: =B7/B5 -> 0.4806921 | C18: =C7/C5 -> 0.47120419 | D18: =D7/D5 -> 0.62765257 | E18: =E7/E5 -> 0.62264151

Sheet Synergies
A1: SYNERGIES ANALYSIS — JPM / SCHW Merger ($M)
A3: Synergy Item | B3: Year 1 | C3: Year 2 | D3: Year 3 | E3: Year 4 | F3: Year 5 (Steady State) | G3: Commentary
A4: REVENUE SYNERGIES
A5: Cross-Sell Wealth Mgmt to Schwab Clients | B5: 200 | C5: 400 | D5: 600 | E5: 750 | F5: 900 | G5: JPM Private Bank access to 34M Schwab accounts; assumed 5-yr ramp
A6: JPM Investment Banking to Schwab Corporates | B6: 100 | C6: 200 | D6: 300 | E6: 350 | F6: 400 | G6: SCHW corporate clients introduced to JPM IB advisory
A7: Deposit & NII Synergies (Balance Sheet) | B7: 500 | C7: 900 | D7: 1200 | E7: 1400 | F7: 1500 | G7: Schwab $400B client cash → JPM balance sheet at higher NII yield
A8: Total Revenue Synergies | B8: =B5+B6+B7 -> 800 | C8: =C5+C6+C7 -> 1500 | D8: =D5+D6+D7 -> 2100 | E8: =E5+E6+E7 -> 2500 | F8: =F5+F6+F7 -> 2800
A10: COST SYNERGIES (PRE-TAX)
A11: Overlapping Technology & Infrastructure | B11: 300 | C11: 600 | D11: 900 | E11: 1100 | F11: 1200 | G11: Consolidate trading platforms, custody systems, data centers
A12: Headcount Reduction (Overlap Functions) | B12: 400 | C12: 700 | D12: 1000 | E12: 1200 | F12: 1300 | G12: Back-office, compliance, finance; ~5,000 FTE reduction at steady state
A13: Vendor & Procurement Consolidation | B13: 100 | C13: 200 | D13: 300 | E13: 350 | F13: 400 | G13: Scale benefits across SCHW vendor contracts
A14: Branch / Real Estate Optimization | B14: 50 | C14: 100 | D14: 200 | E14: 250 | F14: 300 | G14: Schwab branches co-located or converted to JPM branches
A15: Total Cost Synergies | B15: =SUM(B11:B14) -> 850 | C15: =SUM(C11:C14) -> 1600 | D15: =SUM(D11:D14) -> 2400 | E15: =SUM(E11:E14) -> 2900 | F15: =SUM(F11:F14) -> 3200
A17: ONE-TIME INTEGRATION COSTS (CHARGES)
A18: Technology Integration & Migration | B18: 800 | C18: 400 | D18: 200 | E18: 0 | F18: 0
A19: Severance & Restructuring | B19: 600 | C19: 400 | D19: 150 | E19: 0 | F19: 0
A20: Brand & Marketing Transition | B20: 100 | C20: 80 | D20: 50 | E20: 0 | F20: 0
A21: Total Integration Costs (Charges) | B21: =SUM(B18:B20) -> 1500 | C21: =SUM(C18:C20) -> 880 | D21: =SUM(D18:D20) -> 400 | E21: =SUM(E18:E20) -> 0 | F21: =SUM(F18:F20) -> 0
A23: NET SYNERGIES (AFTER INTEGRATION COSTS)
A24: Total Revenue Synergies | B24: =B8 -> 800 | C24: =C8 -> 1500 | D24: =D8 -> 2100 | E24: =E8 -> 2500 | F24: =F8 -> 2800
A25: Total Cost Synergies | B25: =B15 -> 850 | C25: =C15 -> 1600 | D25: =D15 -> 2400 | E25: =E15 -> 2900 | F25: =F15 -> 3200
A26: (-) Integration Costs | B26: =B21 -> 1500 | C26: =C21 -> 880 | D26: =D21 -> 400 | E26: =E21 -> 0 | F26: =F21 -> 0
A27: Net Pre-Tax Synergies | B27: =B24+B25-B26 -> 150 | C27: =C24+C25-C26 -> 2220 | D27: =D24+D25-D26 -> 4100 | E27: =E24+E25-E26 -> 5400 | F27: =F24+F25-F26 -> 6000
A28: After-Tax Synergies (25%) | B28: =B27*0.75 -> 112.5 | C28: =C27*0.75 -> 1665 | D28: =D27*0.75 -> 3075 | E28: =E27*0.75 -> 4050 | F28: =F27*0.75 -> 4500
A30: NPV OF SYNERGIES (Discount Rate: 10%)
A31: Discount Rate | B31: 0.1
A32: PV of After-Tax Synergies (Sum, 5-Year) | B32: =B28/(1+$B$31)^1+C28/(1+$B$31)^2+D28/(1+$B$31)^3+E28/(1+$B$31)^4+F28/(1+$B$31)^5 -> 9348.9492
A33: Terminal Value of Synergies [TV = SS Synergy×(1+2%) / (r-2%)] | B33: =F28*(1+0.02)/($B$31-0.02)/(1+$B$31)^5 -> 35625.361
A34: NPV of Total Synergies ($M) | B34: =B32+B33 -> 44974.31

Sheet Accretion Dilution
A1: ACCRETION / DILUTION ANALYSIS — JPMorgan Chase (Acquirer) ($M, except EPS)
A3: Line Item | B3: JPM Standalone (FY2025E) | C3: SCHW Contribution | D3: + Revenue Synergies (Y3) | E3: + Cost Synergies (Y3) | F3: Pro Forma Combined
A4: PRO FORMA INCOME STATEMENT BUILD
A5: Net Revenue ($M) | B5: ='Standalone Financials'!C5 -> 191000 | C5: ='Standalone Financials'!E5 -> 21200 | D5: =Synergies!D8 -> 2100 | E5: 0 | F5: =B5+C5+D5+E5 -> 214300
A6: (-) Provision for Credit Losses ($M) | B6: ='Standalone Financials'!C6 -> 9500 | C6: ='Standalone Financials'!E6 -> 0 | D6: 0 | E6: 0 | F6: =B6+C6+D6+E6 -> 9500
A7: (-) Non-Interest Expense ($M) | B7: ='Standalone Financials'!C7 -> 90000 | C7: ='Standalone Financials'!E7 -> 13200 | D7: 0 | E7: =-Synergies!D15 -> -2400 | F7: =B7+C7+D7+E7 -> 100800
A8: (-) Integration Charges (Year 3 only) | B8: 0 | C8: 0 | D8: 0 | E8: =Synergies!D21 -> 400 | F8: =B8+C8+D8+E8 -> 400
A9: (-) Incremental D&A (Purchase Price Step-Up) | B9: 0 | C9: 0 | D9: 0 | E9: 800 | F9: =B9+C9+D9+E9 -> 800
A10: (-) Incremental Financing Cost (Cash Portion) | B10: 0 | C10: 0 | D10: 0 | E10: ='Deal Terms'!B20*0.05 -> 2.4975 | F10: =B10+C10+D10+E10 -> 2.4975
A12: Pre-Tax Income ($M) | B12: =B5-B6-B7-B8-B9-B10 -> 91500 | C12: =C5-C6-C7-C8-C9-C10 -> 8000 | D12: =D5-D6-D7-D8-D9-D10 -> 2100 | E12: =E5-E6-E7-E8-E9-E10 -> 1197.5025 | F12: =F5-F6-F7-F8-F9-F10 -> 102797.5
A13: (-) Income Taxes (21.3%) | B13: =B12*0.213 -> 19489.5 | C13: =C12*0.213 -> 1704 | D13: =D12*0.213 -> 447.3 | E13: =E12*0.213 -> 255.06803 | F13: =F12*0.213 -> 21895.868
A14: Pro Forma Net Income ($M) | B14: =B12-B13 -> 72010.5 | C14: =C12-C13 -> 6296 | D14: =D12-D13 -> 1652.7 | E14: =E12-E13 -> 942.43447 | F14: =F12-F13 -> 80901.634
A16: SHARE COUNT & EPS
A17: JPM Diluted Shares (M) — Standalone | B17: ='Deal Terms'!B25 -> 2850 | C17: ='Deal Terms'!B25 -> 2850 | D17: ='Deal Terms'!B25 -> 2850 | E17: ='Deal Terms'!B25 -> 2850 | F17: ='Deal Terms'!B25 -> 2850
A18: (+) New Shares Issued for SCHW | B18: 0 | C18: 0 | D18: 0 | E18: 0 | F18: ='Deal Terms'!B24 -> 485.625
A19: Pro Forma Diluted Shares (M) | B19: =B17+B18 -> 2850 | C19: =C17+C18 -> 2850 | D19: =D17+D18 -> 2850 | E19: =E17+E18 -> 2850 | F19: =F17+F18 -> 3335.625
A21: EPS ACCRETION / DILUTION
A22: Standalone JPM EPS ($) [from IS] | B22: =B14/B19*1000 -> 25266.842 | C22: — | D22: — | E22: — | F22: —
A23: Pro Forma EPS ($) | B23: — | C23: — | D23: — | E23: — | F23: =F14/F19*1000 -> 24253.816
A25: EPS Accretion / (Dilution) ($) | F25: =F23-B22 -> -1013.0263
A26: EPS Accretion / (Dilution) (%) | F26: =IF(B22=0,0,F23/B22-1) -> -0.040093109
A28: Key Assumptions in This Analysis
B29: Year 3 synergies used as representative run-rate for pro forma (standard IB practice)
B30: Includes D&A step-up from fair value of acquired assets (~$800M/yr estimated)
B31: Tax rate held at JPM's FY2024 effective rate of 21.3% for combined entity
B32: =F26 -> -0.040093109

Sheet Sensitivity
A1: SENSITIVITY ANALYSIS — EPS Accretion / (Dilution)
A3: Each cell shows EPS accretion / (dilution) at a given offer price (rows) and % stock consideration (cols). Year 3 cost and revenue synergies held constant. Base case highlighted yellow.
A5: EPS Accretion / (Dilution) — Offer Price vs. % Stock Consideration
A6: Offer Price ($) ↓ % Stock → | B6: 0.5 | C6: 0.6 | D6: 0.7 | E6: 0.8 | F6: 0.9
A7: 80 | B7: =(('Standalone Financials'!C10+'Standalone Financials'!E10+Synergies!D8+Synergies!D15-Synergies!D21-800-(80*'Deal Terms'!B5/1000*0.5)*0.05)*(1-0.213))/('Deal Terms'!B25+'Deal Terms'!B5*80/'Deal Terms'!B22*0.5)*1000-'Accretion Dilution'!B22 -> -4873.0738 | C7: =(('Standalone Financials'!C10+'Standalone Financials'!E10+Synergies!D8+Synergies!D15-Synergies!D21-800-(80*'Deal Terms'!B5/1000*0.4)*0.05)*(1-0.213))/('Deal Terms'!B25+'Deal Terms'!B5*80/'Deal Terms'!B22*0.6)*1000-'Accretion Dilution'!B22 -> -5254.0892 | D7: =(('Standalone Financials'!C10+'Standalone Financials'!E10+Synergies!D8+Synergies!D15-Synergies!D21-800-(80*'Deal Terms'!B5/1000*0.3)*0.05)*(1-0.213))/('Deal Terms'!B25+'Deal Terms'!B5*80/'Deal Terms'!B22*0.7)*1000-'Accretion Dilution'!B22 -> -5621.1224 | E7: =(('Standalone Financials'!C10+'Standalone Financials'!E10+Synergies!D8+Synergies!D15-Synergies!D21-800-(80*'Deal Terms'!B5/1000*0.2)*0.05)*(1-0.213))/('Deal Terms'!B25+'Deal Terms'!B5*80/'Deal Terms'!B22*0.8)*1000-'Accretion Dilution'!B22 -> -5974.9291 | F7: =(('Standalone Financials'!C10+'Standalone Financials'!E10+Synergies!D8+Synergies!D15-Synergies!D21-800-(80*'Deal Terms'!B5/1000*0.1)*0.05)*(1-0.213))/('Deal Terms'!B25+'Deal Terms'!B5*80/'Deal Terms'!B22*0.9)*1000-'Accretion Dilution'!B22 -> -6316.2118
A8: 85 | B8: =(('Standalone Financials'!C10+'Standalone Financials'!E10+Synergies!D8+Synergies!D15-Synergies!D21-800-(85*'Deal Terms'!B5/1000*0.5)*0.05)*(1-0.213))/('Deal Terms'!B25+'Deal Terms'!B5*85/'Deal Terms'!B22*0.5)*1000-'Accretion Dilution'!B22 -> -4993.8028 | C8: =(('Standalone Financials'!C10+'Standalone Financials'!E10+Synergies!D8+Synergies!D15-Synergies!D21-800-(85*'Deal Terms'!B5/1000*0.4)*0.05)*(1-0.213))/('Deal Terms'!B25+'Deal Terms'!B5*85/'Deal Terms'!B22*0.6)*1000-'Accretion Dilution'!B22 -> -5393.4329 | D8: =(('Standalone Financials'!C10+'Standalone Financials'!E10+Synergies!D8+Synergies!D15-Synergies!D21-800-(85*'Deal Terms'!B5/1000*0.3)*0.05)*(1-0.213))/('Deal Terms'!B25+'Deal Terms'!B5*85/'Deal Terms'!B22*0.7)*1000-'Accretion Dilution'!B22 -> -5777.6051 | E8: =(('Standalone Financials'!C10+'Standalone Financials'!E10+Synergies!D8+Synergies!D15-Synergies!D21-800-(85*'Deal Terms'!B5/1000*0.2)*0.05)*(1-0.213))/('Deal Terms'!B25+'Deal Terms'!B5*85/'Deal Terms'!B22*0.8)*1000-'Accretion Dilution'!B22 -> -6147.1994 | F8: =(('Standalone Financials'!C10+'Standalone Financials'!E10+Synergies!D8+Synergies!D15-Synergies!D21-800-(85*'Deal Terms'!B5/1000*0.1)*0.05)*(1-0.213))/('Deal Terms'!B25+'Deal Terms'!B5*85/'Deal Terms'!B22*0.9)*1000-'Accretion Dilution'!B22 -> -6503.0301
A9: 87.5 | B9: =(('Standalone Financials'!C10+'Standalone Financials'!E10+Synergies!D8+Synergies!D15-Synergies!D21-800-(87.5*'Deal Terms'!B5/1000*0.5)*0.05)*(1-0.213))/('Deal Terms'!B25+'Deal Terms'!B5*87.5/'Deal Terms'!B22*0.5)*1000-'Accretion Dilution'!B22 -> -5053.6332 | C9: =(('Standalone Financials'!C10+'Standalone Financials'!E10+Synergies!D8+Synergies!D15-Synergies!D21-800-(87.5*'Deal Terms'!B5/1000*0.4)*0.05)*(1-0.213))/('Deal Terms'!B25+'Deal Terms'!B5*87.5/'Deal Terms'!B22*0.6)*1000-'Accretion Dilution'!B22 -> -5462.3798 | D9: =(('Standalone Financials'!C10+'Standalone Financials'!E10+Synergies!D8+Synergies!D15-Synergies!D21-800-(87.5*'Deal Terms'!B5/1000*0.3)*0.05)*(1-0.213))/('Deal Terms'!B25+'Deal Terms'!B5*87.5/'Deal Terms'!B22*0.7)*1000-'Accretion Dilution'!B22 -> -5854.9156 | E9: =(('Standalone Financials'!C10+'Standalone Financials'!E10+Synergies!D8+Synergies!D15-Synergies!D21-800-(87.5*'Deal Terms'!B5/1000*0.2)*0.05)*(1-0.213))/('Deal Terms'!B25+'Deal Terms'!B5*87.5/'Deal Terms'!B22*0.8)*1000-'Accretion Dilution'!B22 -> -6232.1861 | F9: =(('Standalone Financials'!C10+'Standalone Financials'!E10+Synergies!D8+Synergies!D15-Synergies!D21-800-(87.5*'Deal Terms'!B5/1000*0.1)*0.05)*(1-0.213))/('Deal Terms'!B25+'Deal Terms'!B5*87.5/'Deal Terms'!B22*0.9)*1000-'Accretion Dilution'!B22 -> -6595.0648
A10: 90 | B10: =(('Standalone Financials'!C10+'Standalone Financials'!E10+Synergies!D8+Synergies!D15-Synergies!D21-800-(90*'Deal Terms'!B5/1000*0.5)*0.05)*(1-0.213))/('Deal Terms'!B25+'Deal Terms'!B5*90/'Deal Terms'!B22*0.5)*1000-'Accretion Dilution'!B22 -> -5113.1115 | C10: =(('Standalone Financials'!C10+'Standalone Financials'!E10+Synergies!D8+Synergies!D15-Synergies!D21-800-(90*'Deal Terms'!B5/1000*0.4)*0.05)*(1-0.213))/('Deal Terms'!B25+'Deal Terms'!B5*90/'Deal Terms'!B22*0.6)*1000-'Accretion Dilution'!B22 -> -5530.8502 | D10: =(('Standalone Financials'!C10+'Standalone Financials'!E10+Synergies!D8+Synergies!D15-Synergies!D21-800-(90*'Deal Terms'!B5/1000*0.3)*0.05)*(1-0.213))/('Deal Terms'!B25+'Deal Terms'!B5*90/'Deal Terms'!B22*0.7)*1000-'Accretion Dilution'!B22 -> -5931.6153 | E10: =(('Standalone Financials'!C10+'Standalone Financials'!E10+Synergies!D8+Synergies!D15-Synergies!D21-800-(90*'Deal Terms'!B5/1000*0.2)*0.05)*(1-0.213))/('Deal Terms'!B25+'Deal Terms'!B5*90/'Deal Terms'!B22*0.8)*1000-'Accretion Dilution'!B22 -> -6316.4207 | F10: =(('Standalone Financials'!C10+'Standalone Financials'!E10+Synergies!D8+Synergies!D15-Synergies!D21-800-(90*'Deal Terms'!B5/1000*0.1)*0.05)*(1-0.213))/('Deal Terms'!B25+'Deal Terms'!B5*90/'Deal Terms'!B22*0.9)*1000-'Accretion Dilution'!B22 -> -6686.2012
A11: 92.5 | B11: =(('Standalone Financials'!C10+'Standalone Financials'!E10+Synergies!D8+Synergies!D15-Synergies!D21-800-(92.5*'Deal Terms'!B5/1000*0.5)*0.05)*(1-0.213))/('Deal Terms'!B25+'Deal Terms'!B5*92.5/'Deal Terms'!B22*0.5)*1000-'Accretion Dilution'!B22 -> -5172.2411 | C11: =(('Standalone Financials'!C10+'Standalone Financials'!E10+Synergies!D8+Synergies!D15-Synergies!D21-800-(92.5*'Deal Terms'!B5/1000*0.4)*0.05)*(1-0.213))/('Deal Terms'!B25+'Deal Terms'!B5*92.5/'Deal Terms'!B22*0.6)*1000-'Accretion Dilution'!B22 -> -5598.8489 | D11: =(('Standalone Financials'!C10+'Standalone Financials'!E10+Synergies!D8+Synergies!D15-Synergies!D21-800-(92.5*'Deal Terms'!B5/1000*0.3)*0.05)*(1-0.213))/('Deal Terms'!B25+'Deal Terms'!B5*92.5/'Deal Terms'!B22*0.7)*1000-'Accretion Dilution'!B22 -> -6007.7114 | E11: =(('Standalone Financials'!C10+'Standalone Financials'!E10+Synergies!D8+Synergies!D15-Synergies!D21-800-(92.5*'Deal Terms'!B5/1000*0.2)*0.05)*(1-0.213))/('Deal Terms'!B25+'Deal Terms'!B5*92.5/'Deal Terms'!B22*0.8)*1000-'Accretion Dilution'!B22 -> -6399.9131 | F11: =(('Standalone Financials'!C10+'Standalone Financials'!E10+Synergies!D8+Synergies!D15-Synergies!D21-800-(92.5*'Deal Terms'!B5/1000*0.1)*0.05)*(1-0.213))/('Deal Terms'!B25+'Deal Terms'!B5*92.5/'Deal Terms'!B22*0.9)*1000-'Accretion Dilution'!B22 -> -6776.4522
A12: 95 | B12: =(('Standalone Financials'!C10+'Standalone Financials'!E10+Synergies!D8+Synergies!D15-Synergies!D21-800-(95*'Deal Terms'!B5/1000*0.5)*0.05)*(1-0.213))/('Deal Terms'!B25+'Deal Terms'!B5*95/'Deal Terms'!B22*0.5)*1000-'Accretion Dilution'!B22 -> -5231.0248 | C12: =(('Standalone Financials'!C10+'Standalone Financials'!E10+Synergies!D8+Synergies!D15-Synergies!D21-800-(95*'Deal Terms'!B5/1000*0.4)*0.05)*(1-0.213))/('Deal Terms'!B25+'Deal Terms'!B5*95/'Deal Terms'!B22*0.6)*1000-'Accretion Dilution'!B22 -> -5666.3808 | D12: =(('Standalone Financials'!C10+'Standalone Financials'!E10+Synergies!D8+Synergies!D15-Synergies!D21-800-(95*'Deal Terms'!B5/1000*0.3)*0.05)*(1-0.213))/('Deal Terms'!B25+'Deal Terms'!B5*95/'Deal Terms'!B22*0.7)*1000-'Accretion Dilution'!B22 -> -6083.2109 | E12: =(('Standalone Financials'!C10+'Standalone Financials'!E10+Synergies!D8+Synergies!D15-Synergies!D21-800-(95*'Deal Terms'!B5/1000*0.2)*0.05)*(1-0.213))/('Deal Terms'!B25+'Deal Terms'!B5*95/'Deal Terms'!B22*0.8)*1000-'Accretion Dilution'!B22 -> -6482.6732 | F12: =(('Standalone Financials'!C10+'Standalone Financials'!E10+Synergies!D8+Synergies!D15-Synergies!D21-800-(95*'Deal Terms'!B5/1000*0.1)*0.05)*(1-0.213))/('Deal Terms'!B25+'Deal Terms'!B5*95/'Deal Terms'!B22*0.9)*1000-'Accretion Dilution'!B22 -> -6865.8308
A13: 97.5 | B13: =(('Standalone Financials'!C10+'Standalone Financials'!E10+Synergies!D8+Synergies!D15-Synergies!D21-800-(97.5*'Deal Terms'!B5/1000*0.5)*0.05)*(1-0.213))/('Deal Terms'!B25+'Deal Terms'!B5*97.5/'Deal Terms'!B22*0.5)*1000-'Accretion Dilution'!B22 -> -5289.4658 | C13: =(('Standalone Financials'!C10+'Standalone Financials'!E10+Synergies!D8+Synergies!D15-Synergies!D21-800-(97.5*'Deal Terms'!B5/1000*0.4)*0.05)*(1-0.213))/('Deal Terms'!B25+'Deal Terms'!B5*97.5/'Deal Terms'!B22*0.6)*1000-'Accretion Dilution'!B22 -> -5733.4507 | D13: =(('Standalone Financials'!C10+'Standalone Financials'!E10+Synergies!D8+Synergies!D15-Synergies!D21-800-(97.5*'Deal Terms'!B5/1000*0.3)*0.05)*(1-0.213))/('Deal Terms'!B25+'Deal Terms'!B5*97.5/'Deal Terms'!B22*0.7)*1000-'Accretion Dilution'!B22 -> -6158.121 | E13: =(('Standalone Financials'!C10+'Standalone Financials'!E10+Synergies!D8+Synergies!D15-Synergies!D21-800-(97.5*'Deal Terms'!B5/1000*0.2)*0.05)*(1-0.213))/('Deal Terms'!B25+'Deal Terms'!B5*97.5/'Deal Terms'!B22*0.8)*1000-'Accretion Dilution'!B22 -> -6564.7104 | F13: =(('Standalone Financials'!C10+'Standalone Financials'!E10+Synergies!D8+Synergies!D15-Synergies!D21-800-(97.5*'Deal Terms'!B5/1000*0.1)*0.05)*(1-0.213))/('Deal Terms'!B25+'Deal Terms'!B5*97.5/'Deal Terms'!B22*0.9)*1000-'Accretion Dilution'!B22 -> -6954.3496
A14: 100 | B14: =(('Standalone Financials'!C10+'Standalone Financials'!E10+Synergies!D8+Synergies!D15-Synergies!D21-800-(100*'Deal Terms'!B5/1000*0.5)*0.05)*(1-0.213))/('Deal Terms'!B25+'Deal Terms'!B5*100/'Deal Terms'!B22*0.5)*1000-'Accretion Dilution'!B22 -> -5347.5671 | C14: =(('Standalone Financials'!C10+'Standalone Financials'!E10+Synergies!D8+Synergies!D15-Synergies!D21-800-(100*'Deal Terms'!B5/1000*0.4)*0.05)*(1-0.213))/('Deal Terms'!B25+'Deal Terms'!B5*100/'Deal Terms'!B22*0.6)*1000-'Accretion Dilution'!B22 -> -5800.0632 | D14: =(('Standalone Financials'!C10+'Standalone Financials'!E10+Synergies!D8+Synergies!D15-Synergies!D21-800-(100*'Deal Terms'!B5/1000*0.3)*0.05)*(1-0.213))/('Deal Terms'!B25+'Deal Terms'!B5*100/'Deal Terms'!B22*0.7)*1000-'Accretion Dilution'!B22 -> -6232.4484 | E14: =(('Standalone Financials'!C10+'Standalone Financials'!E10+Synergies!D8+Synergies!D15-Synergies!D21-800-(100*'Deal Terms'!B5/1000*0.2)*0.05)*(1-0.213))/('Deal Terms'!B25+'Deal Terms'!B5*100/'Deal Terms'!B22*0.8)*1000-'Accretion Dilution'!B22 -> -6646.0343 | F14: =(('Standalone Financials'!C10+'Standalone Financials'!E10+Synergies!D8+Synergies!D15-Synergies!D21-800-(100*'Deal Terms'!B5/1000*0.1)*0.05)*(1-0.213))/('Deal Terms'!B25+'Deal Terms'!B5*100/'Deal Terms'!B22*0.9)*1000-'Accretion Dilution'!B22 -> -7042.0208
A16: Yellow = Base Case (Offer $92.50, 70% stock/30% cash, Year 3 synergies)
